Workbook

Sheet Student Details
E5: Name | F5: Roll No | G5: Course | H5: Company Assigned
E6: Mathukumilli Mounika Sai | F6: PGBA23006 | G6: Business Analytics | H6: Grasim Industries Ltd

Sheet Balance Sheet
B2: Table 1.1: Balance Sheet of GRASIM INDUSTRIES LTD (India)
B3: (₹ in Crores) | J3: Table 1.2: Balance Sheet & its Contents
B4: Particulars | C4: As at March 31, 2023 | D4: As at March 31, 2022 | E4: As at March 31, 2021 | F4: As at March 31, 2020 | G4: As at March 31, 2019 | J4: As at March 31, 2023 | K4: As at March 31, 2022 | L4: As at March 31, 2021 | M4: As at March 31, 2020 | N4: As at March 31, 2019
B5: ASSETS
B6: Non-Current Assets
B7: Property, Plant and Equipment | C7: 63753.53 | D7: 58148.57 | E7: 53767.33 | F7: 55758.44 | G7: 55652.22 | I7: PPE | J7: =C7/C43 -> 0.18906459 | K7: =D7/D43 -> 0.20093161 | L7: =E7/E43 -> 0.20133331 | M7: =F7/F43 -> 0.22812944 | N7: =G7/G43 -> 0.23075554
B8: Capital Work-in-progress | C8: 7730.18 | D8: 6572.18 | E8: 5719.43 | F8: 3822.45 | G8: 2728.2 | I8: Capital WIP | J8: =C8/C43 -> 0.022924273 | K8: =D8/D43 -> 0.022710081 | L8: =E8/E43 -> 0.021416569 | M8: =F8/F43 -> 0.015639128 | N8: =G8/G43 -> 0.011312168
B9: Investment Property | C9: 14.37 | D9: 14.81 | E9: 15.24 | F9: 15.67 | G9: 16.11
B10: Goodwill | C10: 20137.55 | D10: 20058.5 | E10: 20013.86 | F10: 20046.5 | G10: 21346.39
B11: Other Intangible Assets | C11: 8591.89 | D11: 8895.41 | E11: 9254.48 | F11: 9684.29 | G11: 10114.47 | I11: Intangible Assets | J11: =(C10+C11+C12+C13)/C43 -> 0.092454048 | K11: =(D10+D11+D12+D13)/D43 -> 0.1066905 | L11: =(E10+E11+E12+E13)/E43 -> 0.11716439 | M11: =(F10+F11+F12+F13)/F43 -> 0.13041342 | N11: =(G10+G11+G12+G13)/G43 -> 0.13060545
B12: Intangible Assets under Development | C12: 47.5 | D12: 42.94 | E12: 49.26 | F12: 81.68 | G12: 37.77
B13: Right of Use Assets | C13: 2399.03 | D13: 1878.83 | E13: 1971.89 | F13: 2062.63
B14: Investment in Equity Accounted Investees | C14: 11016.84 | D14: 7050.17 | E14: 6837.66 | F14: 6533.09 | G14: 6284.29
B15: Financial Assets
B16: Investments | I16: Financial Assets | J16: =(C17+C18+C19+C20+C21+C22)/C43 -> 0.44633652 | K16: =(D17+D18+D19+D20+D21+D22)/D43 -> 0.43326019 | L16: =(E17+E18+E19+E20+E21+E22)/E43 -> 0.39655861 | M16: =(F17+F18+F19+F20+F21+F22)/F43 -> 0.36696785 | N16: =(G17+G18+G19+G20+G21+G22)/G43 -> 0.37852769
B17: Investments of Insurance Business | C17: 39523.43 | D17: 30952.64 | E17: 25046.58 | F17: 19269.34 | G17: 15601.37
B18: Other Investments | C18: 9502.9 | D18: 13881.17 | E18: 10592.62 | F18: 6211.67 | G18: 8751.22
B19: Asset Held to Cover Linked Liabilities of Life Insurance Business | C19: 26842.95 | D19: 26137.33 | E19: 23251.2 | F19: 17638.81 | G19: 20234.85
B20: Trade Receivables | C20: 6.82
B21: Loans | C21: 70871.12 | D21: 51954.12 | E21: 45743.75 | F21: 46054.89 | G21: 46384.67
B22: Other Financial Assets | C22: 3759.7 | D22: 2458 | E22: 1269.33 | F22: 518.03 | G22: 318.9
B23: Deferred Tax Assets (Net) | C23: 382.26 | D23: 246.04 | E23: 205.44 | F23: 137.57 | G23: 46.95 | I23: Deferred Tax Assets (Net) | J23: =C23/C43 -> 0.001133613 | K23: =D23/D43 -> 0.00085018796 | L23: =E23/E43 -> 0.00076927596 | M23: =F23/F43 -> 0.00056285232 | N23: =G23/G43 -> 0.00019467278
B24: Non-current Tax Assets (Net) | C24: 826.38 | D24: 989.16 | E24: 683.73 | F24: 672.89 | G24: 245.78 | I24: Other NCAs
B25: Other Current Tax Assets | C25: 4276.22 | D25: 3347.27 | E25: 2857.15 | F25: 3562.51 | G25: 3530.17 | I25: Current Tax Assets | J25: =C25/C43 -> 0.012681365 | K25: =D25/D43 -> 0.011566447 | L25: =E25/E43 -> 0.01069868 | M25: =F25/F43 -> 0.014575613 | N25: =G25/G43 -> 0.014637444
B26: Total Non-current Assets | C26: 269682.67 | D26: 232627.14 | E26: 207278.95 | F26: 192070.46 | G26: 191293.36 | I26: Total Non-Current Assets | J26: =C26/C43 -> 0.79975874 | K26: =D26/D43 -> 0.80384 | L26: =E26/E43 -> 0.77616196 | M26: =F26/F43 -> 0.78583488 | N26: =G26/G43 -> 0.79317595
B27: Current Assets | I27: Current Assets:-
B28: Inventories | C28: 11159.15 | D28: 9536.42 | E28: 6196.96 | F28: 6805.57 | G28: 7059.13 | I28: Inventories | J28: =C28/C43 -> 0.033093071 | K28: =D28/D43 -> 0.032952973 | L28: =E28/E43 -> 0.023204694 | M28: =F28/F43 -> 0.027844231 | N28: =G28/G43 -> 0.029269872
B29: Financial Assets | I29: Financial Assets
B30: Investments | I30: Investments
B31: Investments of Insurance Business | C31: 900.69 | D31: 2339.22 | E31: 2088.62 | F31: 993.53 | G31: 931.12 | I31: Investments of Insurance Business | J31: =C31/C43 -> 0.0026710456 | K31: =D31/D43 -> 0.0080831437 | L31: =E31/E43 -> 0.0078208974 | M31: =F31/F43 -> 0.0040649172 | N31: =G31/G43 -> 0.0038607821
B32: Other Investments | C32: 13905.64 | D32: 12382.87 | E32: 15482.11 | F32: 10500.75 | G32: 6012.98 | I32: Other Investments | J32: =C32/C43 -> 0.041237938 | K32: =D32/D43 -> 0.042788843 | L32: =E32/E43 -> 0.057973204 | M32: =F32/F43 -> 0.042962648 | N32: =G32/G43 -> 0.024932131
B33: Asset Held to Cover Linked Liabilities of Life Insurance Business | C33: 3662.84 | D33: 4022.72 | E33: 4717.99 | F33: 5189.98 | G33: 4931.49 | I33: Asset Held to Cover Linked Liabilities of Life Insurance Business | J33: =C33/C43 -> 0.010862353 | K33: =D33/D43 -> 0.013900456 | L33: =E33/E43 -> 0.017666649 | M33: =F33/F43 -> 0.021234225 | N33: =G33/G43 -> 0.020447857
B34: Trade Receivables | C34: 5915.1 | D34: 5429.36 | E34: 4341.78 | F34: 5651.5 | G34: 6690.07 | I34: Trade Receivables | J34: =C34/C43 -> 0.017541553 | K34: =D34/D43 -> 0.018761082 | L34: =E34/E43 -> 0.01625792 | M34: =F34/F43 -> 0.023122482 | N34: =G34/G43 -> 0.027739607
B35: Cash and Cash Equivalents | C35: 2312.56 | D35: 2240.7 | E35: 2617.04 | F35: 3072.8 | G35: 1223.69 | I35: Cash and Bank Balances | J35: =(C35+C36)/C43 -> 0.011012232 | K35: =(D35+D36)/D43 -> 0.011239143 | L35: =(E35+E36)/E43 -> 0.018593981 | M35: =(F35+F36)/F43 -> 0.015600874 | N35: =(G35+G36)/G43 -> 0.0079122565
B36: Bank Balances other than Cash and Cash Equivalents | C36: 1400.82 | D36: 1011.85 | E36: 2348.6 | F36: 740.3 | G36: 684.54
B37: Loans | C37: 22342.08 | D37: 14247.01 | E37: 14682.07 | F37: 14175 | G37: 17192.24 | I37: Loans | J37: =C37/C43 -> 0.066256663 | K37: =D37/D43 -> 0.049230354 | L37: =E37/E43 -> 0.054977432 | M37: =F37/F43 -> 0.057995432 | N37: =G37/G43 -> 0.071285648
B38: Other Financial Assets | C38: 2348.92 | D38: 2773.76 | E38: 2579.23 | F38: 1697.98 | G38: 1607.19 | I38: Other Financial Assets | J38: =C38/C43 -> 0.006965851 | K38: =D38/D43 -> 0.0095846909 | L38: =E38/E43 -> 0.0096580006 | M38: =F38/F43 -> 0.0069470959 | N38: =G38/G43 -> 0.0066640287
B39: Current Tax Assets (Net) | C39: 3.27 | D39: 0.11 | E39: 0.12 | F39: 0.38 | G39: 38.71
B40: Other Current Assets | C40: 3553.27 | D40: 2774.14 | E40: 2404.03 | F40: 2440.34 | G40: 2414.68 | I40: Other Current Assets | J40: =C40/C43 -> 0.010537417 | K40: =D40/D43 -> 0.009586004 | L40: =E40/E43 -> 0.0090019592 | M40: =F40/F43 -> 0.0099843791 | N40: =G40/G43 -> 0.010012193
B41: Total Current Assets | C41: 67504.34 | D41: 56758.16 | E41: 57458.55 | I41: Total Current Assets | J41: =C41/C43 -> 0.20018782 | K41: =D41/D43 -> 0.19612707 | L41: =E41/E43 -> 0.21515519 | M41: =F41/F43 -> 0 | N41: =G41/G43 -> 0
B42: Non-Current Assets/ Disposal Group Held for Sale | C42: 18.02 | D42: 9.53 | E42: 2318.81 | F42: 1077.21 | G42: 1094.73
B43: Total Assets | C43: 337205.03 | D43: 289394.83 | E43: 267056.31 | F43: 244415.8 | G43: 241173.93 | I43: Total Assets
B44: EQUITY AND LIABILITIES | I44: Equity and Liabilities
B45: Equity | I45: Equity
B46: Equity Share Capital | C46: 131.69 | D46: 131.67 | E46: 131.62 | F46: 131.57 | G46: 131.53 | I46: Equity Share Capital | J46: =C46/C43 -> 0.00039053391 | K46: =D46/D43 -> 0.00045498394 | L46: =E46/E43 -> 0.00049285486 | M46: =F46/F43 -> 0.00053830399 | N46: =G46/G43 -> 0.00054537404
B47: Other Equity | C47: 78610.3 | D47: 75566.56 | E47: 65362.44 | F47: 56520.76 | G47: 57887.99 | I47: Other Equity | J47: =C47/C43 -> 0.23312315 | K47: =D47/D43 -> 0.26111925 | L47: =E47/E43 -> 0.24475153 | M47: =F47/F43 -> 0.23124839 | N47: =G47/G43 -> 0.2400259
B48: Equity Attributable to Owners of the Company | C48: 78741.99 | D48: 75698.23 | E48: 65494.06 | F48: 56652.33 | G48: 58019.52
B49: Non-Controlling Interest | C49: 44170.83 | D49: 40476.48 | E49: 37067.54 | F49: 34335.42 | G49: 30502.58
B50: Total Equity | C50: 122912.82 | D50: 116174.71 | E50: 102561.6 | F50: 90987.75 | G50: 88522.1 | I50: Total Equity | J50: =C50/C43 -> 0.36450471 | K50: =D50/D43 -> 0.40144017 | L50: =E50/E43 -> 0.38404485 | M50: =F50/F43 -> 0.37226624 | N50: =G50/G43 -> 0.36704672
B51: Liabilities | I51: Liabilities
B52: Non-current liabilities | I52: Non-current liabilities
B53: Financial Liabilities
B54: Borrowings | C54: 66712.46 | D54: 46545.96 | E54: 52488.25 | F54: 58745.91 | G54: 56686.1 | I54: Financial Liabilities | J54: =(C54+C55+C56+C57)/C43 -> 0.40193288 | K54: =(D54+D55+D56+D57)/D43 -> 0.36628063 | L54: =(E54+E55+E56+E57)/E43 -> 0.38745158 | M54: =(F54+F55+F56+F57)/F43 -> 0.40653264 | N54: =(G54+G55+G56+G57)/G43 -> 0.39268059
B55: Lease Liabilities | C55: 1410.73 | D55: 1319.38 | E55: 1447.48 | F55: 1366.14
B56: Policyholder's Liabilities | C56: 67012.03 | D56: 57705.64 | E56: 48991.25 | F56: 38915.8 | G56: 37669.48
B57: Other Financial Liabilities | C57: 398.57 | D57: 428.74 | E57: 544.41 | F57: 335.15 | G57: 348.74
B58: Provisions | C58: 765.81 | D58: 732.94 | E58: 424.58 | F58: 314.99 | G58: 252.25 | I58: Provisions | J58: =C58/C43 -> 0.0022710515 | K58: =D58/D43 -> 0.0025326645 | L58: =E58/E43 -> 0.001589852 | M58: =F58/F43 -> 0.0012887465 | N58: =G58/G43 -> 0.0010459257
B59: Deferred Tax Liabilities (Net) | C59: 8443.38 | D59: 8526.67 | E59: 8456.65 | F59: 6997.06 | G59: 8842.78 | I59: Deferred Tax Liabilities (Net) | J59: =C59/C43 -> 0.025039306 | K59: =D59/D43 -> 0.029463795 | L59: =E59/E43 -> 0.031666168 | M59: =F59/F43 -> 0.028627691 | N59: =G59/G43 -> 0.036665572
B60: Other Non-current Liabilities | C60: 16.24 | D60: 76.32 | E60: 132.19 | F60: 127.09 | G60: 87.03 | I60: Other Non-current Liabilities | J60: =C60/C43 -> 4.816061e-05 | K60: =D60/D43 -> 0.00026372275 | L60: =E60/E43 -> 0.00049498924 | M60: =F60/F43 -> 0.00051997457 | N60: =G60/G43 -> 0.0003608599
B61: Total Non-current liabilities | C61: 144759.22 | D61: 115335.65 | E61: 112484.81 | I61: Total Non-current liabilities | J61: =C61/C43 -> 0.4292914 | K61: =D61/D43 -> 0.39854081 | L61: =E61/E43 -> 0.42120259 | M61: =F61/F43 -> 0 | N61: =G61/G43 -> 0
B62: Current Liabilities | I62: Current Liabilities
B63: Financial Liabilities | I63: Financial Liabilities | J63: =(C64+C65+C66+C67)/C43 -> 0.10970557 | K63: =(D64+D65+D66+D67)/D43 -> 0.10382559 | L63: =(E64+E65+E66+E67)/E43 -> 0.051462517 | M63: =(F64+F65+F66+F67)/F43 -> 0.05945839 | N63: =(G64+G65+G66+G67)/G43 -> 0.086489696
B64: Borrowings | C64: 34635.46 | D64: 26457.29 | E64: 10037.04 | F64: 11988.13 | G64: 18378.52
B65: Lease Liabilities | C65: 279.91 | D65: 238.16 | E65: 221.13 | F65: 195.7
B66: Supplier's Credit | D66: 183.4
B67: Policyholder's Liabilities | C67: 2077.9 | D67: 3167.74 | E67: 3485.22 | F67: 2348.74 | G67: 2480.54
B68: Trade Payables
B69: - Total Outstanding dues of Micro and Small Enterprises | C69: 351.52 | D69: 244.28 | E69: 150.94 | F69: 83.15 | G69: 36.36 | I69: Trade Payables | J69: =(C69+C70)/C43 -> 0.039599854 | K69: =(D69+D70)/D43 -> 0.039369881 | L69: =(E69+E70)/E43 -> 0.030415159 | M69: =(F69+F70)/F43 -> 0.02736562 | N69: =(G69+G70)/G43 -> 0.025225363
B70: - Total Outstanding dues of creditors other than Micro and Small Enterprises | C70: 13001.75 | D70: 11149.16 | E70: 7971.62 | F70: 6605.44 | G70: 6047.34
B71: Other Financial Liabilities | C71: 9859.01 | D71: 8166.09 | E71: 21647.19 | F71: 17920.54 | G71: 14419.25 | I71: Other Financial Liabilities | J71: =C71/C43 -> 0.029237435 | K71: =D71/D43 -> 0.028217816 | L71: =E71/E43 -> 0.081058523 | M71: =F71/F43 -> 0.073319892 | N71: =G71/G43 -> 0.059787764
B72: Other Current Liabilities | C72: 6438.15 | D72: 6445.02 | E72: 5587.44 | F72: 4561.06 | G72: 4779.31 | I72: Other Current Liabilities | J72: =C72/C43 -> 0.019092687 | K72: =D72/D43 -> 0.022270681 | L72: =E72/E43 -> 0.020922329 | M72: =F72/F43 -> 0.018661069 | N72: =G72/G43 -> 0.01981686
B73: Provisions | C73: 722.47 | D73: 815.74 | E73: 1080.15 | F73: 1311.82 | G73: 1230.93 | I73: Provisions | J73: =C73/C43 -> 0.0021425244 | K73: =D73/D43 -> 0.0028187788 | L73: =E73/E43 -> 0.0040446526 | M73: =F73/F43 -> 0.0053671653 | N73: =G73/G43 -> 0.0051039099
B74: Current Tax Liabilities (Net) | C74: 2166.82 | D74: 1017.59 | E74: 1243.21 | F74: 1122.33 | G74: 904.2 | I74: Current Tax Liabilities (Net) | J74: =C74/C43 -> 0.0064258235 | K74: =D74/D43 -> 0.0035162688 | L74: =E74/E43 -> 0.0046552354 | M74: =F74/F43 -> 0.0045918881 | N74: =G74/G43 -> 0.0037491614
B75: Total Current liabilities | C75: 69532.99 | D75: 57884.47 | E75: 51423.94 | F75: =SUM(F64:F74) -> 46136.91 | G75: =SUM(G64:G74) -> 48276.45 | I75: Total Current liabilities | J75: =C75/C43 -> 0.20620389 | K75: =D75/D43 -> 0.20001902 | L75: =E75/E43 -> 0.19255842 | M75: =F75/F43 -> 0.18876402 | N75: =G75/G43 -> 0.20017275
B76: Liabilities directly associated with Non-Current Assets Held for Sale | E76: 585.96 | F76: 489 | G76: 489
B77: Total Liabilities | C77: =C61+C75 -> 214292.21 | D77: =D61+D75 -> 173220.12 | E77: =E61+E75 -> 163908.75 | F77: =F61+F75 -> 46136.91 | G77: =G61+G75 -> 48276.45 | I77: Total Liabilities | J77: =C77/C43 -> 0.63549529 | K77: =D77/D43 -> 0.59855983 | L77: =E77/E43 -> 0.61376101 | M77: =F77/F43 -> 0.18876402 | N77: =G77/G43 -> 0.20017275
B78: Total Equity and Liabilities | C78: 337205.03 | D78: 289394.83 | E78: 267056.31 | F78: 244415.8 | G78: 241173.93 | I78: Total Equity and Liabilities
B83: No. of Equity Shares (in Crores) | C83: 65.84 | D83: 65.84 | E83: 65.84 | F83: 65.84 | G83: 65.84
B84: MPS (INR) | C84: 1632.7 | D84: 1664 | E84: 1450.55 | F84: 476.1 | G84: 830.15
B85: Value per Share (Book Value) | C85: =C50/C83 -> 1866.8411 | D85: =D50/D83 -> 1764.5005 | E85: =E50/E83 -> 1557.74 | F85: =F50/F83 -> 1381.9525 | G85: =G50/G83 -> 1344.5033
B86: Price to Book Value (P/BV) Ratio | H86: current MPS/P/BV Ratio | J86: Book Value = Total Equity/ No. of equity shares
B107: MPS (INR) as of Sept 1, 2023 (Rs)
B109: Price to Book Value (P/BV) Ratio as of Sep 1, 2023
B111: Tangible Value of the Firm (Total Equity - Intangible Assets)
B113: Tangible Value per Share (Tangible Value / No. of Equity Shares)
B116: Ex: Calculation of Liquidation Value:
B117: Realisable Value of the Assets
B118: Total Liabilities (Non CL + CL)
B119: Liquidation Value (Realisable value of the assets -Total Liabilities)
B120: Liquidation value per share (Liquidation value/ no. of equity shares)
B123: Liquidity Position (TCA/TCL)
B124: Total Current Assets/ Total Current Liabilities)

Sheet Statement of P & L
B2: Table 2.1: Statement of Profit and Loss of Grasim Industries Ltd. (India) | J2: Table 2.2: Statement of Profit and Loss & its contents | Q2: Table 2.3: Analysis of Satement of Profit and Loss
B3: for the year ended (₹ in Crores) | J3: Particulars | K3: March 31, 2023 | L3: March 31, 2022 | M3: March 31, 2021 | N3: March 31, 2020 | O3: March 31, 2019 | Q3: Particulars | R3: March 31, 2023 | S3: March 31, 2022 | T3: March 31, 2021 | U3: March 31, 2020 | V3: March 31, 2019
B4: Particulars | C4: March 31, 2023 | D4: March 31, 2022 | E4: March 31, 2021 | F4: March 31, 2020 | G4: March 31, 2019 | Q4: Growth in Revenue from Operations | R4: =(C5/D5)-1 -> 0.22910858 | S4: =(D5/E5)-1 -> 0.2526685 | T4: =(E5/F5)-1 -> -0.015810479 | U4: =(F5/G5)-1 -> 0.0055032205
B5: Revenue from operations | C5: 117627.08 | D5: 95701.13 | E5: 76397.81 | F5: 77625.1 | G5: 77200.25 | J5: Revenue from operations (% of Total Income) | K5: =C5/C7 -> 0.97020723 | L5: =D5/D7 -> 0.99149069 | M5: =E5/E7 -> 0.98641752 | N5: =F5/F7 -> 0.98770087 | O5: =G5/G7 -> 0.98939239
B6: Other Income | C6: 3612.05 | D6: 821.34 | E6: 1051.96 | F6: 966.61 | G6: 827.69 | J6: Other income (% of Total Income) | K6: =C6/C7 -> 0.029792774 | L6: =D6/D7 -> 0.0085093139 | M6: =E6/E7 -> 0.013582481 | N6: =F6/F7 -> 0.012299134 | O6: =G6/G7 -> 0.010607611
B7: Total Income (I) | C7: 121239.13 | D7: 96522.47 | E7: 77449.77 | F7: 78591.71 | G7: 78027.94 | Q7: Growth in Net Income (PAT) | R7: =(C33/D33)-1 -> 0.036260997 | S7: =(D33/E33)-1 -> 0.58396353 | T7: =(E33/F33)-1 -> 0.010746569 | U7: =(F33/G33)-1 -> 1.4328279
B8: Expenses
B9: Cost of materials consumed | C9: 21622.26 | D9: 16889.6 | E9: 11006.75 | F9: 14618.05 | G9: 15261.12 | J9: Material Expenses (% of Revenue from Operations) | K9: =(C9+C10+C11)/C5 -> 0.20642585 | L9: =(D9+D10+D11)/D5 -> 0.20079073 | M9: =(E9+E10+E11)/E5 -> 0.16530867 | N9: =(F9+F10+F11)/F5 -> 0.21402626 | O9: =(G9+G10+G11)/G5 -> 0.21823789 | Q9: Operating Profit (EBIT) | R9: =C5-C17+C21 -> 219536.97 | S9: =D5-D17+D21 -> 176427.66 | T9: =E5-E17+E21 -> 140009.04 | U9: =F5-F17+F21 -> 144162.28 | V9: =G5-G17+G21 -> 143355.21
B10: Purchases of stock-in-trade | C10: 1824.35 | D10: 1404.56 | E10: 898.44 | F10: 1469.86 | G10: 1507.01
B11: Changes in inventories of finished goods, work-in-progress and stock-in-trade | C11: 834.66 | D11: 921.74 | E11: 724.03 | F11: 525.9 | G11: 79.89 | Q11: Operating Profit Margin (EBIT/ Revenue from Operations) | R11: =R9/C5 -> 1.8663812 | S11: =S9/D5 -> 1.8435274 | T11: =T9/E5 -> 1.8326316 | U11: =U9/F5 -> 1.8571606 | V11: =V9/G5 -> 1.8569268
B12: Employee benefits expense | C12: 7193.86 | D12: 6327.71 | E12: 5534.74 | F12: 5864.53 | G12: 5428.21 | J12: Employee benefit Exp. (% of Revenue from Operations) | K12: =C12/C5 -> 0.061158196 | L12: =D12/D5 -> 0.066119491 | M12: =E12/E5 -> 0.072446318 | N12: =F12/F5 -> 0.075549403 | O12: =G12/G5 -> 0.070313373
B13: Power and Fuel | C13: 23168.73 | D13: 15520.7 | E13: 10363.78 | F13: 11436.68 | G13: 12423.45
B14: Freight and Handling Expenses | C14: 15024.93 | D14: 12584.1 | E14: 10381.83 | F14: 10058.06 | G14: 10619.15
B15: Change in Valuation of Liability in respect of Insurance Policies | C15: 7451.57 | D15: 4240.83 | E15: 4374.84 | F15: 1032.26 | G15: 1408.88
B16: Benefits Paid - Insurance Business | C16: 5467.75 | D16: 6702.55 | E16: 4445.05 | F16: 5177.01 | G16: 4553.57
B17: Finance Cost relating to NBFC/HFC's Business | C17: 4723.46 | D17: 3480.3 | E17: 3914.6 | F17: 4587.82 | G17: 4050.18 | J17: Finance Exp. (% of Revenue from Operations) | K17: =C17/C5 -> 0.040156229 | L17: =D17/D5 -> 0.036366342 | M17: =E17/E5 -> 0.051239689 | N17: =F17/F5 -> 0.059102275 | O17: =G17/G5 -> 0.052463302
B18: Other Finance Costs | C18: 1320.27 | D18: 1295.7 | E18: 1808.88 | F18: 2338.5 | G18: 2009.85
B19: Depreciation and Amortisation expense | C19: 4551.59 | D19: 4161.07 | E19: 4033.4 | F19: 4040.82 | G19: 3571.38 | J19: D & A Exp. (% of Revenue from Operations) | K19: =C19/C5 -> 0.038695086 | L19: =D19/D5 -> 0.043479842 | M19: =E19/E5 -> 0.052794707 | N19: =F19/F5 -> 0.052055585 | O19: =G19/G5 -> 0.046261249 | Q19: EBITDA (EBIT+ D&A) | R19: =R9+C19 -> 224088.56 | S19: =S9+D19 -> 180588.73 | T19: =T9+E19 -> 144042.44 | U19: =U9+F19 -> 148203.1 | V19: =V9+G19 -> 146926.59
B20: Other Expenses | C20: 15119.24 | D20: 12521.45 | E20: 10069.97 | F20: 11047.77 | G20: 9482.99 | J20: Other Exp (% of Revenue from Operations) | K20: =C20/C5 -> 0.12853537 | L20: =D20/D5 -> 0.1308391 | M20: =E20/E5 -> 0.13180967 | N20: =F20/F5 -> 0.14232214 | O20: =G20/G5 -> 0.12283626 | Q20: EBITDA Margin | R20: =R19/C5 -> 1.9050763 | S20: =S19/D5 -> 1.8870073 | T20: =T19/E5 -> 1.8854263 | U20: =U19/F5 -> 1.9092162 | V20: =V19/G5 -> 1.903188
B21: Total Expenses (II) | C21: 106633.35 | D21: 84206.83 | E21: 67525.83 | F21: 71125 | G21: 70205.14 | J21: Total Expenses (% of Revenue from Operations) | K21: =C21/C5 -> 0.90653742 | L21: =D21/D5 -> 0.87989379 | M21: =E21/E5 -> 0.88387128 | N21: =F21/F5 -> 0.91626291 | O21: =G21/G5 -> 0.90939006
B22: Profit from Continuing Operations Before Share in Profit of (I - II) | C22: 14605.78 | D22: 12315.64 | E22: 9923.94 | F22: 7466.71 | G22: 7822.8 | Q22: Other income (% of PAT) | R22: =C6/C33 -> 0.32605026 | S22: =D6/D33 -> 0.076828601 | T22: =E6/E33 -> 0.15586347 | U22: =F6/F33 -> 0.1447567 | V22: =G6/G33 -> 0.30155497
B23: Equity Accounted Investees, Exceptional Items and Tax
B24: Share in Profit of Equity Accounted Investees | C24: 208.96 | D24: 380.33 | E24: 189.22
B25: Profit from Continuing Operations Before Tax and Exceptional Items | C25: 14814.74 | D25: 12695.97 | E25: 10113.16
B26: Exceptional Items | C26: 88.03 | D26: 69.11 | E26: 341.73 | Q26: Avg Assets (Current year Assets + Previous Year Assets)/2 | R26: =('Balance Sheet'!C43+'Balance Sheet'!D43)/2 -> 313299.93 | S26: =('Balance Sheet'!D43+'Balance Sheet'!E43)/2 -> 278225.57 | T26: =('Balance Sheet'!E43+'Balance Sheet'!F43)/2 -> 255736.05 | U26: =('Balance Sheet'!F43+'Balance Sheet'!G43)/2 -> 242794.86 | V26: =('Balance Sheet'!G43+'Balance Sheet'!H43)/2 -> 120586.96
B27: Profit from Continuing Operations Before Tax (PBT) | C27: 14726.71 | D27: 12626.86 | E27: 9771.43 | F27: 562.22 | G27: 29.06 | J27: PBT (% OF Revenue from Operations) | K27: =C27/C5 -> 0.1251983 | L27: =D27/D5 -> 0.13194055 | M27: =E27/E5 -> 0.12790196 | N27: =F27/F5 -> 0.0072427604 | O27: =G27/G5 -> 0.00037642365 | Q27: ROI (PAT/Avg. Assets) | R27: =C33/R26 -> 0.035359727 | S27: =D33/S26 -> 0.038424038 | T27: =E33/T26 -> 0.026391429 | U27: =F33/U26 -> 0.027502559 | V27: =G33/V26 -> 0.022761498
B28: Tax expense | Q28: Average Equity | R28: =('Balance Sheet'!C50+'Balance Sheet'!D50)/2 -> 119543.77 | S28: =('Balance Sheet'!D50+'Balance Sheet'!E50)/2 -> 109368.15 | T28: =('Balance Sheet'!E50+'Balance Sheet'!F50)/2 -> 96774.675 | U28: =('Balance Sheet'!F50+'Balance Sheet'!G50)/2 -> 89754.925 | V28: =('Balance Sheet'!G50+'Balance Sheet'!H50)/2 -> 44261.05
B29: Tax Expense of Continuing Operations (Net)
B30: Current Tax | C30: 3432.67 | D30: 1954.4 | E30: 1959.4 | F30: 1607.38 | G30: 2339.4 | Q30: ROE (PAT/Avg Equity) | R30: =C33/R28 -> 0.092670663 | S30: =D33/S28 -> 0.097748289 | T30: =E33/T28 -> 0.0697418 | U30: =F33/U28 -> 0.074396809 | V30: =G33/V28 -> 0.062012537
B31: Deferred Tax | C31: 215.84 | D31: 18.09 | E31: 1062.79 | F31: 1633.59 | G31: 94.83
B32: Total Tax Expenses | C32: 3648.51 | D32: 1936.31 | E32: 3022.19 | F32: 30.65 | G32: 2418.72 | J32: Total Tax Exp. (% of Revenue from Operations) | K32: =C32/C5 -> 0.031017602 | L32: =D32/D5 -> 0.020232885 | M32: =E32/E5 -> 0.039558595 | N32: =F32/F5 -> 0.00039484651 | O32: =G32/G5 -> 0.031330468 | Q32: P/E (Price to Earnings) Ratio (MPS/EPS) | R32: ='Balance Sheet'!C84/'Statement of P & L'!C71 -> 15.702058 | S32: ='Balance Sheet'!D84/'Statement of P & L'!D71 -> 14.472082 | T32: ='Balance Sheet'!E84/'Statement of P & L'!E71 -> 22.12216 | U32: ='Balance Sheet'!F84/'Statement of P & L'!F71 -> 7.0617028 | V32: ='Balance Sheet'!G84/'Statement of P & L'!G71 -> 32.22632
B33: Profit for the Year from Continuing Operations (III) (PAT) | C33: 11078.2 | D33: 10690.55 | E33: 6749.24 | F33: 6677.48 | G33: 2744.74 | J33: PAT (% of Revenue from Operations) | K33: =C33/C5 -> 0.094180694 | L33: =D33/D5 -> 0.11170767 | M33: =E33/E5 -> 0.08834337 | N33: =F33/F5 -> 0.086022176 | O33: =G33/G5 -> 0.035553512 | Q33: P/S (Price to Sales) Ratio (MPS/Sales per Share) | R33: ='Balance Sheet'!C84/'Statement of P & L'!R42 -> 0.91387942 | S33: ='Balance Sheet'!D84/'Statement of P & L'!S42 -> 1.1447907 | T33: ='Balance Sheet'!E84/'Statement of P & L'!T42 -> 1.250091 | U33: ='Balance Sheet'!F84/'Statement of P & L'!U42 -> 0.40381815 | V33: ='Balance Sheet'!G84/'Statement of P & L'!V42 -> 0.70799092
B34: Discontinued Operations
B35: Profit Before Tax from Discontinued Operations | D35: 352.52 | E35: 162.79 | F35: 90.03 | G35: 54.94
B36: Exceptional Items | D36: 670.71 | E36: 166.5 | F36: 36.63 | G36: 15.31
B37: Tax Expenses of Discontinued Operations | D37: 440.07 | E37: 66.1
B38: Less: Reversal / (Provision) of Impairment of Assets Classified as Held for Sale | D38: 67.42 | E38: 25.73 | F38: 53.4 | G38: 39.63
B39: Profit for the Year from Discontinued Operations (IV) | D39: 515.74 | E39: 237.46
B40: Profit for the Year (V = III + IV) | C40: 11078.2 | D40: 11206.29 | E40: 6986.7 | F40: 6677.48 | G40: 2744.74
B41: Other Comprehensive Income (net of Tax) | J41: PBIT (PBT+ Finance Cost) | K41: =C27+C17 -> 19450.17 | L41: =D27+D17 -> 16107.16 | M41: =E27+E17 -> 13686.03 | N41: =F27+F17 -> 5150.04 | O41: =G27+G17 -> 4079.24
B42: A (i) Items that will not be reclassified to Profit or Loss | C42: 3444.28 | D42: 3442.16 | E42: 6986.7 | F42: 5512.19 | G42: 2689.45 | J42: PBIT (% of Revenue from Operations) | K42: =K41/C5 -> 0.16535453 | L42: =L41/D5 -> 0.16830689 | M42: =M41/E5 -> 0.17914165 | N42: =N41/F5 -> 0.066345035 | O42: =O41/G5 -> 0.052839725 | Q42: Sales per Share (Revenue from Operations/No. of Equity shares) | R42: ='Statement of P & L'!C5/'Balance Sheet'!C83 -> 1786.5595 | S42: ='Statement of P & L'!D5/'Balance Sheet'!D83 -> 1453.5409 | T42: ='Statement of P & L'!E5/'Balance Sheet'!E83 -> 1160.3556 | U42: ='Statement of P & L'!F5/'Balance Sheet'!F83 -> 1178.9961 | V42: ='Statement of P & L'!G5/'Balance Sheet'!G83 -> 1172.5433
B43: (ii) Income Tax relating to items that will not be reclassified to Profit or Loss | C43: 387.85 | D43: 221.77 | E43: 387.07 | F43: 373.62 | G43: 31.06
B44: B (i) Items that will be reclassified to Profit or Loss | C44: 182.04 | D44: 63.88 | E44: 163.53 | F44: 145.53 | G44: 77.38
B45: (ii) Income Tax relating to items that will be reclassified to Profit or Loss | C45: 57.69 | D45: 3.47 | E45: 18.75 | F45: 8.96 | G45: 16.63
B46: Other Comprehensive Income for the Year (VI) | C46: 3180.78 | D46: 3280.8 | E46: 4840.92 | F46: 5002 | G46: 2781.26
B47: Total comprehensive income for the Year (V+VI) | C47: 7897.42 | D47: 14487.09 | E47: 11827.62 | F47: 1675.48 | G47: 36.52
B48: Profit from Continuing Operations Attributable to:
B49: Owners of the Company | C49: 6827.26 | D49: 7102.37 | E49: 4128.41 | F49: 4425.19 | G49: 1692.99
B50: Non-Controlling Interest | C50: 4250.94 | D50: 3588.18 | E50: 2620.83 | F50: 2252.29 | G50: 1051.75
C51: 11078.2 | D51: 10690.55 | E51: 6749.24 | F51: 6677.48 | G51: 2744.74
B52: Profit Attributable to:
B53: Owners of the Company | C53: 6827.26 | D53: 7549.78 | E53: 4304.82 | F53: 4425.19 | G53: 1692.99
B54: Non-Controlling Interest | C54: 4250.94 | D54: 3656.51 | E54: 2681.88 | F54: 2252.29 | G54: 1051.75
C55: 11078.2 | D55: 11206.29 | E55: 6986.7 | F55: 6677.48 | G55: 2744.74
B56: Other Comprehensive Income Attributable to:
B57: Owners of the Company | C57: 3104.23 | D57: 3281.85 | E57: 4780.54 | F57: 5067.74 | G57: 2822.5
B58: Non-Controlling Interest | C58: 76.55 | D58: 1.05 | E58: 60.38 | F58: 65.74 | G58: 41.24
C59: 3180.78 | D59: 3280.8 | E59: 4840.92 | F59: 5002 | G59: 2781.26
B60: Total Comprehensive Income Attributable to:
B61: Owners of the Company | C61: 3723.03 | D61: 10831.63 | E61: 9085.36 | F61: 642.55 | G61: 1129.51
B62: Non-Controlling Interest | C62: 4174.39 | D62: 3655.46 | E62: 2742.26 | F62: 2318.03 | G62: 1092.99
C63: 7897.42 | D63: 14487.09 | E63: 11827.62 | F63: 1675.48 | G63: 36.52
B64: Earnings Per Equity Share (Face Value D 2 each) - Continuing Operations
B65: Basic (₹) | C65: 103.98 | D65: 108.16 | E65: 62.88 | F65: 67.42 | G65: 25.76
B66: Diluted (₹) | C66: 103.88 | D66: 108 | E66: 62.82 | F66: 67.38 | G66: 25.74
B67: Earnings Per Equity Share (Face Value D 2 each) - Discontinued Operations
B68: Basic (₹) | D68: 6.82 | E68: 2.69
B69: Diluted (₹) | D69: 6.8 | E69: 2.68
B70: Earnings Per Equity Share (Face Value D 2 each) - Continuing and Discontinued Operations
B71: Basic (₹) | C71: 103.98 | D71: 114.98 | E71: 65.57 | F71: 67.42 | G71: 25.76
B72: Diluted (₹) | C72: 103.88 | D72: 114.8 | E72: 65.5 | F72: 67.38 | G72: 25.74

Sheet Statement of CFS
B2: Table 3.1: Statement of Cash Flows of Grasim Industries Ltd. (India)
B3: for the year ended (₹ in Crores)
B4: Particulars | C4: March 31, 2023 | D4: March 31, 2022 | E4: March 31, 2021 | F4: March 31, 2020 | G4: March 31, 2019
B5: A. Cash flow from Operating Activities:
B6: Profit Before Tax after Exceptional Items and before Share in Profit/(Loss) of Equity Accounted Investees | C6: 14517.75 | D6: 12246.53 | E6: 9582.21 | F6: 6084.61 | G6: 5134.4
B7: Adjustments for Continuing Operations:
B8: Exceptional Items | C8: 88.03 | D8: 69.11 | E8: 314.3 | F8: 1382.1 | G8: 2688.4
B9: Depreciation and Amortisation Expenses | C9: 4551.59 | D9: 4161.07 | E9: 4033.4 | F9: 4040.82 | G9: 3571.38
B10: Finance Costs | C10: 1320.27 | D10: 1295.7 | E10: 1808.88 | F10: 2338.5 | G10: 2009.85
B11: Interest Income | C11: 380.58 | D11: 219.62 | E11: 150.57 | F11: 150.51 | G11: 199.19
B12: Dividend Income | C12: 40.4 | D12: 31.28 | E12: 13.89 | F12: 61.54 | G12: 86.48
B13: Unrealised Exchange loss | F13: 18.56 | G13: 30.5
B14: Employee Stock Options and Stock Appreciation Rights Expenses | C14: 118.34 | D14: 66.65 | E14: 39.22 | F14: 73.64 | G14: 117.5
B15: Allowance for Credit Losses on Advances/Debts (Net) | C15: 9.78 | D15: 15.97 | E15: 7.34 | F15: 11.28 | G15: 8.12
B16: Provision for Mines Restoration - (Release)/Charge | F16: 17.15 | G16: 6.29
B17: Changes in Valuation of Liabilities in respect of Insurance Policies in force | C17: 7451.57 | D17: 4240.83 | E17: 4374.83 | F17: 1032.26 | G17: 1408.88
B18: Impairment on Financial Instruments | C18: 983.46 | D18: 731.33 | E18: 772.36 | F18: 780.31 | G18: 322.62
B19: Excess Provision Written Back (Net) | C19: 143.82 | D19: 145.51 | E19: 92.62 | F19: 150.14 | G19: 90.32
B20: Loss on Sale/Discard of Property, Plant and Equipment (Net) | C20: 10.64 | D20: 7.71 | E20: 8.2 | F20: 38.95 | G20: 13.87
B21: Profit on Sale of Investments (Net) | C21: 78.57 | D21: 220.44 | E21: 205.91 | F21: 121.7 | G21: 159.49
B22: Unrealised Gain and Fair Value Adjustments on Investments measured at Fair Value through Profit and Loss (Net) | C22: 339.86 | D22: 640.06 | E22: 1117.39 | F22: 527.26 | G22: 434.51
B23: Unrealised Exchange (Gain)/Loss (Net) | C23: 102.43 | D23: 55.77 | E23: 12.85
B24: Gain on control establishment on Associate | D24: 7.88
B25: Fair Value Adjustments to Borrowings | C25: 50.26 | D25: 74.44 | E25: 48.83
B26: Other Non-Cash Items | C26: 3.77 | E26: 0.84 | F26: 10.09 | G26: 45.96
B27: Gain on account of Fair Value of Investment in Aditya Birla Health Insurance Co. Limited on conversion from Subsidiary to Joint Venture (note 4.12.5) | C27: 2754.77
B28: Operating Profit Before Working Capital Changes | C28: 25165.01 | D28: 21407.96 | E28: 19299.52 | F28: 14817.12 | G28: 14283.28
B29: Adjustment for:
B30: Trade Receivables | C30: 455.24 | D30: 1074.49 | E30: 4.2 | F30: 1027.8 | G30: 1269.51
B31: Loans of Financing Business | C31: 27972.19 | D31: 7100.48 | E31: 2111.39 | F31: 2719.07 | G31: 11643.53
B32: Financial and Other Assets | C32: 1251.53 | D32: 1322.62 | E32: 814.64 | F32: 431.34 | G32: 1161.06
B33: Inventories | C33: 1598.39 | D33: 3340.81 | E33: 3889.76 | F33: 234.47 | G33: 353.67
B34: Trade Payables, Other Liabilities and Provision | C34: 3008.57 | D34: 4830.48 | E34: 4269.65 | F34: 988.85 | G34: 1512.51
B35: Investments of Life Insurance Policyholders | C35: 7486.55 | D35: 3396.75 | E35: 4269.65 | F35: 951.4 | G35: 1153.07
B36: Cash Generated from Operations | C36: 10590.32 | D36: 10003.29 | E36: 16544.82 | F36: 18404.57 | G36: 214.95
B37: Income Taxes Paid (Net of Refund) | C37: 2094.82 | D37: 2965.64 | E37: 1843.94 | F37: 1738.52 | G37: 1873.53
B38: Net Cash generated from Operating Activities (A) | C38: 12685.14 | D38: 7037.65 | E38: 14700.88 | F38: 16666.05 | G38: 1658.58
B39: B. Cash Flow from Investing Activities
B40: Purchase of Property, Plant and Equipment and other Intangible Assets | C40: 12036.16 | D40: 8587.68 | E40: 3651.04 | F40: 5130.36 | G40: 4178.95
B41: Proceeds from Disposal of Property, Plant and Equipment | C41: 111.49 | D41: 82.56 | E41: 98.34 | F41: 94.26 | G41: 170.18
B42: Acquisition of Equity Shares in Subsidiaries | C42: 19.34 | D42: 41.6 | G42: 35.07
B43: Investments in Grasim Premium Fabrics Private Limited (earlier known as Soktas (India) Private Limited) (wholly owned Subsidiary) | F43: 4.33 | G43: 123.98
B44: Contribution towards Liquidation Expenses of Idea Payment Bank Private Limited | F44: 10.2
B45: Investments in Joint Ventures and Associates | C45: 858.73 | D45: 35.16 | E45: 17.55 | F45: 0.05 | G45: 95.22
B46: Sale of Mutual Fund Units, Shares and Bonds (Non-Current) | C46: 6858.23 | D46: 14386.13 | E46: 5617.01 | F46: 3507.26 | G46: 4458.56
B47: Investments in Treasury Shares Held by ESOP Trust | F47: 8.55 | G47: 187.99
B48: Sale of Treasury Share Held by ESOP Trust | E48: 10.09 | F48: 0.51
B49: Purchase of Mutual Fund Units, Shares and Bonds (Non-Current) | C49: 7605.95 | D49: 6613.64 | E49: 12808.56 | F49: 6717.18 | G49: 2007.42
B50: (Purchase)/Sale of Investments and Shareholders' Investment of Life Insurance Business (Current) {Net} | F50: 829.21 | G50: 404.48
B51: Proceeds from (Purchase)/Sale of Investments and Shareholders' Investment of Life Insurance Business (Current) {Net} | C51: 104.76 | D51: 4176.52 | E51: 3374.28
B52: Proceeds from Sale of Non-Current Equity Investment (Subsidiary) | F52: 156.69 | G52: 0.07
B53: Proceeds from sale of Non-Current Equity Investment (Joint Venture) | G53: 35.67
B54: Proceeds on disposal of subsidiaries | C54: 3.49
B55: Purchase of Other Non-Current Investments | C55: 70.19 | D55: 64.77 | E55: 121.25 | F55: 2891.14 | G55: 60.66
B56: Proceeds from Sale of Other Non-Current Investment | C56: 0.1 | F56: 12.55 | G56: 81.34
B57: Redemption/(Investment) in Other Bank Deposits | C57: 689.17 | D57: 1264.97 | E57: 1711.87 | F57: 96.94 | G57: 257.13
B58: Expenditure for Cost of Assets Transferred | D58: 94.57 | E58: 209.51 | F58: 76.53 | G58: 52.32
B59: Loans and Advances given to other Companies | C59: 106.61 | D59: 16.75
B60: Receipt against Loans and Advances given to Other Companies | D60: 12.55
B61: Loans and Advances Given to Joint Ventures and Associates | D61: 5 | E61: 4.2 | G61: 35
B62: Receipt Against Loans and Advances Given to Associates | C62: 112.69 | D62: 7.2 | E62: 6.4 | F62: 2.2 | G62: 35
B63: Inter-Corporate Deposits | G63: 31.88
B64: Interest Received | C64: 312.01 | D64: 191.18 | E64: 115.66 | F64: 125.81 | G64: 178.8
B65: Dividend Received | C65: 196.67 | D65: 147.92 | E65: 85.29 | F65: 229.84 | G65: 239.48
B66: Net Cash Used in Investing Activities (B) | C66: 13686.71 | D66: 3543.18 | E66: 9216.91 | F66: 11635.37 | G66: 2271
B67: C. Cash Flow from Financing Activities
B68: Proceeds from Issue of Share Capital under ESOP Scheme | C68: 16.62 | D68: 8.95 | E68: 12.6 | F68: 9.02 | G68: 8.58
B69: Treasury Shares Acquired by ESOP Trust | C69: 222.57 | D69: 153.14
B70: Proceeds from Issue of Treasury Shares | C70: 18.23 | D70: 19.15
B71: Equity Infusion by Minority Shareholders in Subsidiary Companies | C71: 327.96 | D71: 327.96 | E71: 166.82 | F71: 1511.96 | G71: 171.61
B72: Transaction cost on equity shares of a Subsidiary Company and share Issue Expenses | C72: 3.95 | E72: 0.34 | F72: 4.95 | G72: 1.92
B73: Proceeds from Non-Current Borrowings | C73: 39810.27 | D73: 15178.98 | E73: 15895.19 | F73: 18849.74 | G73: 31166.09
B74: Repayment of Non-Current Borrowings | C74: 16403.82 | D74: 21014.15 | E74: 20737.89 | F74: 14068.98 | G74: 21367.85
B75: Proceeds/(Repayments) of Current Borrowings (Net) | C75: 5748.28 | D75: 1544.38 | E75: 785.05 | F75: 6315.95 | G75: 3266.96
B76: Proceeds of Supplier's Credit | C76: 183.4 | D76: 183.4
B77: Proceeds from Inter-Corporate Loans | C77: 28.6 | D77: 60.93 | E77: 71.42
B78: Repayment of Inter-Corporate Loans | C78: 3 | D78: 50.43 | E78: 70.32
B79: Repayment of Lease Liabilities (including Interest) | C79: 319.73 | D79: 352.93 | E79: 300.9 | F79: 278.73
B80: Interest and Finance Charges Paid | C80: 1193.8 | D80: 1322.55 | E80: 1831.46 | F80: 2174.7 | G80: 1916.75
B81: Dividend Paid | C81: 1150.56 | D81: 1065.5
B82: Dividend paid to Non-Controlling Interest | E82: 11.54 | F82: 7.42 | G82: 9.21
B83: Dividend Paid (including Corporate Dividend Tax) | E83: 422.07 | F83: 705.31 | G83: 625.6
B84: Net Cash Used in Financing Activities | C84: 26469.13 | D84: 6733.13 | E84: 8013.54 | F84: 3185.32 | G84: 4157.99
B85: D. Net Increase/(Decrease) in Cash and Cash Equivalents from Continuing Operations | C85: 97.28 | D85: 3238.67 | E85: 2529.57 | F85: 1845.36 | G85: 228.41
B86: E. Net Cash Flow Transferred from Discontinued Operations to Continuing Operations | D86: 2491.02 | E86: 2082.92
B87: F. Cash and Cash Equivalents as at the beginning of the Year from Continuing Operations | C87: 2240.7 | D87: 2988.74 | E87: 3063.36 | F87: 1223.69 | G87: 936.65
B88: G. Add: Cash and Cash Equivalents Received on acquisition of controlling Stake in Waacox | D88: 0.08
B89: H. Adjustment on account of conversion of Aditya Birla Health Insurance Co. Limited from Subsidiary to Joint Venture | C89: 24.81
B90: I. Add: Effect of Exchange Rate on Consolidation of Foreign Subsidiaries | C90: 0.61 | D90: 0.47 | E90: 0.33 | F90: 3.75 | G90: 0.41
B91: Cash and Cash Equivalents at the end of the Year from Continuing Operations | C91: 2312.56 | D91: 2240.7 | E91: 2617.04 | F91: 3072.8 | G91: 1223.69
B92: Cash and Cash Equivalents Received on acquisition of Ultratech Nathdwara Cement limited and transferred from Century Textiles Industries Limited on demerger of Cement business to UTCL{Note 4.12 (A) & (B)} | G92: 50.91
B93: Cash and Cash Equivalents Received on acquisition of controlling Stake in Aditya Birla Renewables Limited and Aditya Birla Solar Limited {Note 4.12 (C)} | G93: 7.31
B94: J. Cash Flow from Discontinued Operations
B95: Opening Cash and Cash Equivalents | E95: 31.12 | F95: 27.46 | G95: 23.94
B96: Cash Flows generated from/(Used in) Operating Activities | D96: 217.33 | E96: 1398.26 | F96: 34.79 | G96: 57.55
B97: Cash Flows generated from/(Used in) Investing Activities | D97: 48.93 | E97: 686.46 | F97: 8.8 | G97: 54.94
B98: Cash Flows generated from/(Used in) Financing Activities | D98: 901.48 | E98: 32.27 | F98: 30.33 | G98: 0.91
B99: Proceeds from Divestment of Fertiliser Business | D99: 1855.8
B100: Net cash inflows | F100: 23.12 | G100: 3.52
B101: Net Increase in Cash and Cash Equivalents from Discontinuing Operations | D101: 2491.02 | E101: 2083.57
...

Sheet Analysis of CFS
B2: Table 3.1: Statement of Cash Flows of Grasim Industries Ltd. (India)
B3: for the year ended (₹ in Crores) | J3: Analysis of Statement of Cash Flows
B4: Particulars | C4: March 31, 2023 | D4: March 31, 2022 | E4: March 31, 2021 | F4: March 31, 2020 | G4: March 31, 2019 | J4: Check Point | K4: March 31, 2023 | L4: March 31, 2022 | M4: March 31, 2021 | N4: March 31, 2020 | O4: March 31, 2019
B5: A. Cash flow from Operating Activities: | J5: 1. Major source of cash inflow: Cash from Operations | K5: =C38 -> 12685.14 | L5: =D38 -> 7037.65 | M5: =E38 -> 14700.88 | N5: =F38 -> 16666.05 | O5: =G38 -> 1658.58
B6: Profit Before Tax after Exceptional Items and before Share in Profit/(Loss) of Equity Accounted Investees | C6: 14517.75 | D6: 12246.53 | E6: 9582.21 | F6: 6084.61 | G6: 5134.4 | J6: 2. Net cash investment in CapEx | K6: =SUM(C40:C41) -> -11924.67 | L6: =SUM(D40:D41) -> -8505.12 | M6: =SUM(E40:E41) -> -3552.7 | N6: =SUM(F40:F41) -> -5036.1 | O6: =SUM(G40:G41) -> -4008.77
B7: Adjustments for Continuing Operations: | J7: 3. Is Net Cash Flow from Operations sufficient for cash required for Investing activity (Capex)? | K7: Yes | L7: No | M7: Yes | N7: Yes | O7: No
B8: Exceptional Items | C8: 88.03 | D8: 69.11 | E8: 314.3 | F8: 1382.1 | G8: 2688.4 | J8: 4. Net cash flow from Operations required not only for investing activity but also for interest cost payment | K8: 1320.27 | L8: 1295.7 | M8: 1808.88 | N8: 2338.5 | O8: 2009.85
B9: Depreciation and Amortisation Expenses | C9: 4551.59 | D9: 4161.07 | E9: 4033.4 | F9: 4040.82 | G9: 3571.38 | J9: Ans: | K9: Yes | L9: No | M9: Yes | N9: Yes | O9: No | Q9: =K5 -> 12685.14 | R9: =L5 -> 7037.65 | S9: =M5 -> 14700.88 | T9: =N5 -> 16666.05 | U9: =O5 -> 1658.58
B10: Finance Costs | C10: 1320.27 | D10: 1295.7 | E10: 1808.88 | F10: 2338.5 | G10: 2009.85 | J10: Net cash investment in CapEx | K10: =K6 -> -11924.67 | L10: =L6 -> -8505.12 | M10: =M6 -> -3552.7 | N10: =N6 -> -5036.1 | O10: =O6 -> -4008.77 | Q10: =SUM(K10:K11) -> -10604.4 | R10: =SUM(L10:L11) -> -7209.42 | S10: =SUM(M10:M11) -> -1743.82 | T10: =SUM(N10:N11) -> -2697.6 | U10: =SUM(O10:O11) -> -1998.92
B11: Interest Income | C11: 380.58 | D11: 219.62 | E11: 150.57 | F11: 150.51 | G11: 199.19 | J11: Finance Cost (Interest cost) | K11: 1320.27 | L11: 1295.7 | M11: 1808.88 | N11: 2338.5 | O11: 2009.85
B12: Dividend Income | C12: 40.4 | D12: 31.28 | E12: 13.89 | F12: 61.54 | G12: 86.48
B13: Unrealised Exchange loss | F13: 18.56 | G13: 30.5 | J13: 5. Is net cash flow from Operations sufficient for not only cash required for investing activity and interest cost payment but also for dividend payment?
B14: Employee Stock Options and Stock Appreciation Rights Expenses | C14: 118.34 | D14: 66.65 | E14: 39.22 | F14: 73.64 | G14: 117.5 | J14: Ans:
B15: Allowance for Credit Losses on Advances/Debts (Net) | C15: 9.78 | D15: 15.97 | E15: 7.34 | F15: 11.28 | G15: 8.12 | J15: Net cash investment in CapEx | K15: 11925 | L15: 8505 | M15: 3553 | N15: 5036 | O15: 4009
B16: Provision for Mines Restoration - (Release)/Charge | F16: 17.15 | G16: 6.29 | J16: Finance Cost (Interest cost) | K16: =K11 -> 1320.27 | L16: =L11 -> 1295.7 | M16: =M11 -> 1808.88 | N16: =N11 -> 2338.5 | O16: =O11 -> 2009.85
B17: Changes in Valuation of Liabilities in respect of Insurance Policies in force | C17: 7451.57 | D17: 4240.83 | E17: 4374.83 | F17: 1032.26 | G17: 1408.88 | J17: Dividend Payment | K17: =C81+C82+C83 -> 1150.56 | L17: =D81+D82+D83 -> 1065.5 | M17: =E81+E82+E83 -> 867.22 | N17: =F81+F82+F83 -> 1425.46 | O17: =G81+G82+G83 -> 1269.62
B18: Impairment on Financial Instruments | C18: 983.46 | D18: 731.33 | E18: 772.36 | F18: 780.31 | G18: 322.62 | J18: 6. Is investment in Capex greater than depreciation and amortization?
B19: Excess Provision Written Back (Net) | C19: 143.82 | D19: 145.51 | E19: 92.62 | F19: 150.14 | G19: 90.32 | J19: Ans: Yes, Net Cash Investment in CapEx | K19: =K6 -> -11924.67 | L19: =L6 -> -8505.12 | M19: =M6 -> -3552.7 | N19: =N6 -> -5036.1 | O19: =O6 -> -4008.77
B20: Loss on Sale/Discard of Property, Plant and Equipment (Net) | C20: 10.64 | D20: 7.71 | E20: 8.2 | F20: 38.95 | G20: 13.87 | J20: Depreciation and Amortisation Expenses | K20: =C9 -> 4551.59 | L20: =D9 -> 4161.07 | M20: =E9 -> 4033.4 | N20: =F9 -> 4040.82 | O20: =G9 -> 3571.38
B21: Profit on Sale of Investments (Net) | C21: 78.57 | D21: 220.44 | E21: 205.91 | F21: 121.7 | G21: 159.49
B22: Unrealised Gain and Fair Value Adjustments on Investments measured at Fair Value through Profit and Loss (Net) | C22: 339.86 | D22: 640.06 | E22: 1117.39 | F22: 527.26 | G22: 434.51 | J22: 7. Free Cash Flows (FCF)
B23: Unrealised Exchange (Gain)/Loss (Net) | C23: 102.43 | D23: 55.77 | E23: 12.85
B24: Gain on control establishment on Associate | D24: 7.88 | J24: 8. Net amount of working capital adjustments (NWC) | K24: =SUM(C30:C35) -> 41772.47 | L24: =SUM(D30:D35) -> 21065.63 | M24: =SUM(E30:E35) -> 15359.29 | N24: =SUM(F30:F35) -> 6352.93 | O24: =SUM(G30:G35) -> 17093.35
B25: Fair Value Adjustments to Borrowings | C25: 50.26 | D25: 74.44 | E25: 48.83 | J25: 9. Quality of Profit | K25: =C38/'Statement of P & L'!C33 -> 1.1450543 | L25: =D38/'Statement of P & L'!D33 -> 0.6583057 | M25: =E38/'Statement of P & L'!E33 -> 2.1781534 | N25: =F38/'Statement of P & L'!F33 -> 2.4958592 | O25: =G38/'Statement of P & L'!G33 -> 0.60427581
B26: Other Non-Cash Items | C26: 3.77 | E26: 0.84 | F26: 10.09 | G26: 45.96 | J26: Quality of Profit = Cash from Operations/PAT
B27: Gain on account of Fair Value of Investment in Aditya Birla Health Insurance Co. Limited on conversion from Subsidiary to Joint Venture (note 4.12.5) | C27: 2754.77
B28: Operating Profit Before Working Capital Changes | C28: 25165.01 | D28: 21407.96 | E28: 19299.52 | F28: 14817.12 | G28: 14283.28 | J28: FCF = C - I | K28: =K5-K19 -> 24609.81 | L28: =L5-L19 -> 15542.77 | M28: =M5-M19 -> 18253.58 | N28: =N5-N19 -> 21702.15 | O28: =O5-O19 -> 5667.35
B29: Adjustment for: | J29: I (net Fin Exp)
B30: (Decrease) Trade Receivables | C30: 455.24 | D30: 1074.49 | E30: 4.2 | F30: 1027.8 | G30: 1269.51 | J30: C - I - i | K30: =K28 -> 24609.81 | L30: =L28 -> 15542.77 | M30: =M28 -> 18253.58 | N30: =N28 -> 21702.15 | O30: =O28 -> 5667.35
B31: Loans of Financing Business | C31: 27972.19 | D31: 7100.48 | E31: 2111.39 | F31: 2719.07 | G31: 11643.53 | J31: d (net dividend payout) | K31: =-C81 -> -1150.56 | L31: =-D81 -> -1065.5 | M31: =-E81 -> -433.61 | N31: =-F81 -> -712.73 | O31: =-G81 -> -634.81
B32: Financial and Other Assets | C32: 1251.53 | D32: 1322.62 | E32: 814.64 | F32: 431.34 | G32: 1161.06 | J32: Difference | K32: =SUM(K30:K31) -> 23459.25 | L32: =SUM(L30:L31) -> 14477.27 | M32: =SUM(M30:M31) -> 17819.97 | N32: =SUM(N30:N31) -> 20989.42 | O32: =SUM(O30:O31) -> 5032.54
B33: Inventories | C33: 1598.39 | D33: 3340.81 | E33: 3889.76 | F33: 234.47 | G33: 353.67
B34: Trade Payables, Other Liabilities and Provision | C34: 3008.57 | D34: 4830.48 | E34: 4269.65 | F34: 988.85 | G34: 1512.51 | J34: Change in Net working capital (Operating Assets) | K34: =C32+C33+C34 -> 5858.49 | L34: =D32+D33+D34 -> 9493.91 | M34: =E32+E33+E34 -> 8974.05 | N34: =F32+F33+F34 -> 1654.66 | O34: =G32+G33+G34 -> 3027.24
B35: Investments of Life Insurance Policyholders | C35: 7486.55 | D35: 3396.75 | E35: 4269.65 | F35: 951.4 | G35: 1153.07
B36: Cash Generated from Operations | C36: 10590.32 | D36: 10003.29 | E36: 16544.82 | F36: 18404.57 | G36: 214.95
B37: Income Taxes Paid (Net of Refund) | C37: 2094.82 | D37: 2965.64 | E37: 1843.94 | F37: 1738.52 | G37: 1873.53
B38: Net Cash generated from Operating Activities (A) | C38: 12685.14 | D38: 7037.65 | E38: 14700.88 | F38: 16666.05 | G38: 1658.58
B39: B. Cash Flow from Investing Activities
B40: Purchase of Property, Plant and Equipment and other Intangible Assets | C40: -12036.16 | D40: -8587.68 | E40: -3651.04 | F40: -5130.36 | G40: -4178.95
B41: Proceeds from Disposal of Property, Plant and Equipment | C41: 111.49 | D41: 82.56 | E41: 98.34 | F41: 94.26 | G41: 170.18 | J41: Treasurer Rule:
B42: Acquisition of Equity Shares in Subsidiaries | C42: 19.34 | D42: 41.6 | G42: 35.07
B43: Investments in Grasim Premium Fabrics Private Limited (earlier known as Soktas (India) Private Limited) (wholly owned Subsidiary) | F43: 4.33 | G43: 123.98 | J43: C - I - I > d
B44: Contribution towards Liquidation Expenses of Idea Payment Bank Private Limited | F44: 10.2 | J44: C - I - I < d
B45: Investments in Joint Ventures and Associates | C45: 858.73 | D45: 35.16 | E45: 17.55 | F45: 0.05 | G45: 95.22
B46: Sale of Mutual Fund Units, Shares and Bonds (Non-Current) | C46: 6858.23 | D46: 14386.13 | E46: 5617.01 | F46: 3507.26 | G46: 4458.56
B47: Investments in Treasury Shares Held by ESOP Trust | F47: 8.55 | G47: 187.99
B48: Sale of Treasury Share Held by ESOP Trust | E48: 10.09 | F48: 0.51
B49: Purchase of Mutual Fund Units, Shares and Bonds (Non-Current) | C49: 7605.95 | D49: 6613.64 | E49: 12808.56 | F49: 6717.18 | G49: 2007.42 | J49: FCF =
B50: (Purchase)/Sale of Investments and Shareholders' Investment of Life Insurance Business (Current) {Net} | F50: 829.21 | G50: 404.48 | J50: EBIT (1 - Tax) = NOPAT
B51: Proceeds from (Purchase)/Sale of Investments and Shareholders' Investment of Life Insurance Business (Current) {Net} | C51: 104.76 | D51: 4176.52 | E51: 3374.28 | J51: D&A
B52: Proceeds from Sale of Non-Current Equity Investment (Subsidiary) | F52: 156.69 | G52: 0.07 | J52: CapEX
B53: Proceeds from sale of Non-Current Equity Investment (Joint Venture) | G53: 35.67 | J53: Change in WC
B54: Proceeds on disposal of subsidiaries | C54: 3.49
B55: Purchase of Other Non-Current Investments | C55: 70.19 | D55: 64.77 | E55: 121.25 | F55: 2891.14 | G55: 60.66 | J55: FCF = C - I
B56: Proceeds from Sale of Other Non-Current Investment | C56: 0.1 | F56: 12.55 | G56: 81.34 | J56: FCF = NOPAT + D&A-CapEX +/- Change in WC
B57: Redemption/(Investment) in Other Bank Deposits | C57: 689.17 | D57: 1264.97 | E57: 1711.87 | F57: 96.94 | G57: 257.13
B58: Expenditure for Cost of Assets Transferred | D58: 94.57 | E58: 209.51 | F58: 76.53 | G58: 52.32 | J58: FCFE = C - I - i
B59: Loans and Advances given to other Companies | C59: 106.61 | D59: 16.75
B60: Receipt against Loans and Advances given to Other Companies | D60: 12.55 | J60: Value of F = Ve + Vd
B61: Loans and Advances Given to Joint Ventures and Associates | D61: 5 | E61: 4.2 | G61: 35
B62: Receipt Against Loans and Advances Given to Associates | C62: 112.69 | D62: 7.2 | E62: 6.4 | F62: 2.2 | G62: 35
B63: Inter-Corporate Deposits | G63: 31.88
B64: Interest Received | C64: 312.01 | D64: 191.18 | E64: 115.66 | F64: 125.81 | G64: 178.8
B65: Dividend Received | C65: 196.67 | D65: 147.92 | E65: 85.29 | F65: 229.84 | G65: 239.48
B66: Net Cash Used in Investing Activities (B) | C66: 13686.71 | D66: 3543.18 | E66: 9216.91 | F66: 11635.37 | G66: 2271
B67: C. Cash Flow from Financing Activities
B68: Proceeds from Issue of Share Capital under ESOP Scheme | C68: 16.62 | D68: 8.95 | E68: 12.6 | F68: 9.02 | G68: 8.58
B69: Treasury Shares Acquired by ESOP Trust | C69: 222.57 | D69: 153.14
B70: Proceeds from Issue of Treasury Shares | C70: 18.23 | D70: 19.15
B71: Equity Infusion by Minority Shareholders in Subsidiary Companies | C71: 327.96 | D71: 327.96 | E71: 166.82 | F71: 1511.96 | G71: 171.61
B72: Transaction cost on equity shares of a Subsidiary Company and share Issue Expenses | C72: 3.95 | E72: 0.34 | F72: 4.95 | G72: 1.92
B73: Proceeds from Non-Current Borrowings | C73: 39810.27 | D73: 15178.98 | E73: 15895.19 | F73: 18849.74 | G73: 31166.09
B74: Repayment of Non-Current Borrowings | C74: 16403.82 | D74: 21014.15 | E74: 20737.89 | F74: 14068.98 | G74: 21367.85
B75: Proceeds/(Repayments) of Current Borrowings (Net) | C75: 5748.28 | D75: 1544.38 | E75: 785.05 | F75: 6315.95 | G75: 3266.96
B76: Proceeds of Supplier's Credit | C76: 183.4 | D76: 183.4
B77: Proceeds from Inter-Corporate Loans | C77: 28.6 | D77: 60.93 | E77: 71.42
B78: Repayment of Inter-Corporate Loans | C78: 3 | D78: 50.43 | E78: 70.32
B79: Repayment of Lease Liabilities (including Interest) | C79: 319.73 | D79: 352.93 | E79: 300.9 | F79: 278.73
B80: Interest and Finance Charges Paid | C80: 1193.8 | D80: 1322.55 | E80: 1831.46 | F80: 2174.7 | G80: 1916.75
B81: Dividend Paid | C81: 1150.56 | D81: 1065.5 | E81: =E82+E83 -> 433.61 | F81: =SUM(F82:F83) -> 712.73 | G81: =SUM(G82:G83) -> 634.81
B82: Dividend paid to Non-Controlling Interest | E82: 11.54 | F82: 7.42 | G82: 9.21
B83: Dividend Paid (including Corporate Dividend Tax) | E83: 422.07 | F83: 705.31 | G83: 625.6
B84: Net Cash Used in Financing Activities | C84: 26469.13 | D84: 6733.13 | E84: 8013.54 | F84: 3185.32 | G84: 4157.99
B85: D. Net Increase/(Decrease) in Cash and Cash Equivalents from Continuing Operations | C85: 97.28 | D85: 3238.67 | E85: 2529.57 | F85: 1845.36 | G85: 228.41
B86: E. Net Cash Flow Transferred from Discontinued Operations to Continuing Operations | D86: 2491.02 | E86: 2082.92
B87: F. Cash and Cash Equivalents as at the beginning of the Year from Continuing Operations | C87: 2240.7 | D87: 2988.74 | E87: 3063.36 | F87: 1223.69 | G87: 936.65
B88: G. Add: Cash and Cash Equivalents Received on acquisition of controlling Stake in Waacox | D88: 0.08
B89: H. Adjustment on account of conversion of Aditya Birla Health Insurance Co. Limited from Subsidiary to Joint Venture | C89: 24.81
B90: I. Add: Effect of Exchange Rate on Consolidation of Foreign Subsidiaries | C90: 0.61 | D90: 0.47 | E90: 0.33 | F90: 3.75 | G90: 0.41
B91: Cash and Cash Equivalents at the end of the Year from Continuing Operations | C91: 2312.56 | D91: 2240.7 | E91: 2617.04 | F91: 3072.8 | G91: 1223.69
B92: Cash and Cash Equivalents Received on acquisition of Ultratech Nathdwara Cement limited and transferred from Century Textiles Industries Limited on demerger of Cement business to UTCL{Note 4.12 (A) & (B)} | G92: 50.91
B93: Cash and Cash Equivalents Received on acquisition of controlling Stake in Aditya Birla Renewables Limited and Aditya Birla Solar Limited {Note 4.12 (C)} | G93: 7.31
B94: J. Cash Flow from Discontinued Operations
B95: Opening Cash and Cash Equivalents | E95: 31.12 | F95: 27.46 | G95: 23.94
B96: Cash Flows generated from/(Used in) Operating Activities | D96: 217.33 | E96: 1398.26 | F96: 34.79 | G96: 57.55
B97: Cash Flows generated from/(Used in) Investing Activities | D97: 48.93 | E97: 686.46 | F97: 8.8 | G97: 54.94
B98: Cash Flows generated from/(Used in) Financing Activities | D98: 901.48 | E98: 32.27 | F98: 30.33 | G98: 0.91
B99: Proceeds from Divestment of Fertiliser Business | D99: 1855.8
B100: Net cash inflows | F100: 23.12 | G100: 3.52
B101: Net Increase in Cash and Cash Equivalents from Discontinuing Operations | D101: 2491.02 | E101: 2083.57
...

Sheet Vertical Analysis of BS
B2: Table 1.1: Balance Sheet of GRASIM INDUSTRIES LTD (India) | I2: Vertical Analysis (Common Size Analysis) of Balance Sheet
B3: (₹ in Crores) | I3: (Each item as a % of Total Assets)
B4: Particulars | C4: As at March 31, 2023 | D4: As at March 31, 2022 | E4: As at March 31, 2021 | F4: As at March 31, 2020 | G4: As at March 31, 2019 | J4: As at March 31, 2023 | K4: As at March 31, 2022 | L4: As at March 31, 2021 | M4: As at March 31, 2020 | N4: As at March 31, 2019
B5: ASSETS | J5: % | K5: % | L5: % | M5: % | N5: %
B6: Non-Current Assets
B7: Property, Plant and Equipment | C7: 63753.53 | D7: 58148.57 | E7: 53767.33 | F7: 55758.44 | G7: 55652.22 | I7: PPE | J7: =C7/$C$47 -> 0.18906459 | K7: =D7/$D$47 -> 0.20093161 | L7: =E7/$E$47 -> 0.20133331 | M7: =F7/$F$47 -> 0.22812944 | N7: =G7/$G$47 -> 0.23075554
B8: Capital Work-in-progress | C8: 7730.18 | D8: 6572.18 | E8: 5719.43 | F8: 3822.45 | G8: 2728.2 | I8: Capital WIP | J8: =C8/$C$47 -> 0.022924273 | K8: =D8/$D$47 -> 0.022710081 | L8: =E8/$E$47 -> 0.021416569 | M8: =F8/$F$47 -> 0.015639128 | N8: =G8/$G$47 -> 0.011312168
B9: Investment Property | C9: 14.37 | D9: 14.81 | E9: 15.24 | F9: 15.67 | G9: 16.11 | I9: Intangible Assets | J9: =(C10+C11+C15+C16)/$C$47 -> 0.092454048 | K9: =(D10+D11+D15+D16)/$D$47 -> 0.1066905 | L9: =(E10+E11+E15+E16)/$E$47 -> 0.11716439 | M9: =(F10+F11+F15+F16)/$F$47 -> 0.13041342 | N9: =(G10+G11+G15+G16)/$G$47 -> 0.13060545
B10: Goodwill | C10: 20137.55 | D10: 20058.5 | E10: 20013.86 | F10: 20046.5 | G10: 21346.39
B11: Other Intangible Assets | C11: 8591.89 | D11: 8895.41 | E11: 9254.48 | F11: 9684.29 | G11: 10114.47 | I11: Financial Assets | J11: =C20/$C$47 -> 0.1172089 | K11: =D20/$D$47 -> 0.10695644 | L11: =E20/$E$47 -> 0.093787636 | M11: =F20/$F$47 -> 0.078838357 | N11: =G20/$G$47 -> 0.064689289
J12: =C21/$C$47 -> 0.028181371 | K12: =D21/$D$47 -> 0.047966199 | L12: =E21/$E$47 -> 0.039664369 | M12: =F21/$F$47 -> 0.025414355 | N12: =G21/$G$47 -> 0.036285929
J13: =C22/$C$47 -> 0.07960424 | K13: =D22/$D$47 -> 0.090317197 | L13: =E22/$E$47 -> 0.087064784 | M13: =F22/$F$47 -> 0.072167225 | N13: =G22/$G$47 -> 0.083901481
J14: =C23/$C$47 -> 2.0225084e-05 | K14: =D23/$D$47 -> 0 | L14: =E23/$E$47 -> 0 | M14: =F23/$F$47 -> 0 | N14: =G23/$G$47 -> 0
B15: Intangible Assets under Development | C15: 47.5 | D15: 42.94 | E15: 49.26 | F15: 81.68 | G15: 37.77 | J15: =C24/$C$47 -> 0.21017219 | K15: =D24/$D$47 -> 0.17952677 | L15: =E24/$E$47 -> 0.17128878 | M15: =F24/$F$47 -> 0.18842845 | N15: =G24/$G$47 -> 0.19232871
B16: Right of Use Assets | C16: 2399.03 | D16: 1878.83 | E16: 1971.89 | F16: 2062.63 | J16: =C25/$C$47 -> 0.011149596 | K16: =D25/$D$47 -> 0.0084935864 | L16: =E25/$E$47 -> 0.0047530425 | M16: =F25/$F$47 -> 0.002119462 | N16: =G25/$G$47 -> 0.0013222822
B17: Investment in Equity Accounted Investees | C17: 11016.84 | D17: 7050.17 | E17: 6837.66 | F17: 6533.09 | G17: 6284.29
B18: Financial Assets | I18: Other NCAs
B19: Investments | I19: Current Tax Assets | J19: =C43/C47 -> 9.6973642e-06 | K19: =D43/D47 -> 3.8010354e-07 | L19: =E43/E47 -> 4.4934344e-07 | M19: =F43/F47 -> 1.5547276e-06 | N19: =G43/G47 -> 0.00016050657
B20: Investments of Insurance Business | C20: 39523.43 | D20: 30952.64 | E20: 25046.58 | F20: 19269.34 | G20: 15601.37 | I20: Total Non-CAs | J20: =C29/$C$47 -> 0.79975874 | K20: =D29/$D$47 -> 0.80384 | L20: =E29/$E$47 -> 0.77616196 | M20: =F29/$F$47 -> 0.78583488 | N20: =G29/$G$47 -> 0.79317595
B21: Other Investments | C21: 9502.9 | D21: 13881.17 | E21: 10592.62 | F21: 6211.67 | G21: 8751.22
B22: Asset Held to Cover Linked Liabilities of Life Insurance Business | C22: 26842.95 | D22: 26137.33 | E22: 23251.2 | F22: 17638.81 | G22: 20234.85 | I22: Inventories | J22: =C31/C47 -> 0.033093071 | K22: =D31/D47 -> 0.032952973 | L22: =E31/E47 -> 0.023204694 | M22: =F31/F47 -> 0.027844231 | N22: =G31/G47 -> 0.029269872
B23: Trade Receivables | C23: 6.82
B24: Loans | C24: 70871.12 | D24: 51954.12 | E24: 45743.75 | F24: 46054.89 | G24: 46384.67 | I24: Trade Receivables | J24: =C37/C47 -> 0.017541553 | K24: =D37/D47 -> 0.018761082 | L24: =E37/E47 -> 0.01625792 | M24: =F37/F47 -> 0.023122482 | N24: =G37/G47 -> 0.027739607
B25: Other Financial Assets | C25: 3759.7 | D25: 2458 | E25: 1269.33 | F25: 518.03 | G25: 318.9 | I25: Cash & Bank Balances | J25: =C38/C47 -> 0.0068580234 | K25: =D38/D47 -> 0.0077427092 | L25: =E38/E47 -> 0.0097995812 | M25: =F38/F47 -> 0.012572019 | N25: =G38/G47 -> 0.00507389
B26: Deferred Tax Assets (Net) | C26: 382.26 | D26: 246.04 | E26: 205.44 | F26: 137.57 | G26: 46.95 | J26: =C39/C47 -> 0.0041542085 | K26: =D39/D47 -> 0.0034964343 | L26: =E39/E47 -> 0.0087944 | M26: =F39/F47 -> 0.0030288549 | N26: =G39/G47 -> 0.0028383665
B27: Non-current Tax Assets (Net) | C27: 826.38 | D27: 989.16 | E27: 683.73 | F27: 672.89 | G27: 245.78 | I27: Loans & Advances
B28: Other Current Tax Assets | C28: 4276.22 | D28: 3347.27 | E28: 2857.15 | F28: 3562.51 | G28: 3530.17 | I28: Other FA | J28: =C25/C47 -> 0.011149596 | K28: =D25/D47 -> 0.0084935864 | L28: =E25/E47 -> 0.0047530425 | M28: =F25/F47 -> 0.002119462 | N28: =G25/G47 -> 0.0013222822
B29: Total Non-current Assets | C29: 269682.67 | D29: 232627.14 | E29: 207278.95 | F29: 192070.46 | G29: 191293.36 | I29: Other CAs | J29: =C44/C47 -> 0.010537417 | K29: =D44/D47 -> 0.009586004 | L29: =E44/E47 -> 0.0090019592 | M29: =F44/F47 -> 0.0099843791 | N29: =G44/G47 -> 0.010012193
B30: Current Assets | I30: Total CAs | J30: =C45/C47 -> 0.20018782 | K30: =D45/D47 -> 0.19612707 | L30: =E45/E47 -> 0.21515519 | M30: =F45/F47 -> 0 | N30: =G45/G47 -> 0
B31: Inventories | C31: 11159.15 | D31: 9536.42 | E31: 6196.96 | F31: 6805.57 | G31: 7059.13 | I31: Total Assets | J31: =C47/C47 -> 1 | K31: =D47/D47 -> 1 | L31: =E47/E47 -> 1 | M31: =F47/F47 -> 1 | N31: =G47/G47 -> 1
B32: Financial Assets
B33: Investments
B34: Investments of Insurance Business | C34: 900.69 | D34: 2339.22 | E34: 2088.62 | F34: 993.53 | G34: 931.12 | I34: Equity Share Capital | J34: =C50/C82 -> 0.00039053391 | K34: =D50/D82 -> 0.00045498394 | L34: =E50/E82 -> 0.00049285486 | M34: =F50/F82 -> 0.00053830399 | N34: =G50/G82 -> 0.00054537404
B35: Other Investments | C35: 13905.64 | D35: 12382.87 | E35: 15482.11 | F35: 10500.75 | G35: 6012.98 | I35: Other Equity | J35: =C51/C82 -> 0.23312315 | K35: =D51/D82 -> 0.26111925 | L35: =E51/E82 -> 0.24475153 | M35: =F51/F82 -> 0.23124839 | N35: =G51/G82 -> 0.2400259
B36: Asset Held to Cover Linked Liabilities of Life Insurance Business | C36: 3662.84 | D36: 4022.72 | E36: 4717.99 | F36: 5189.98 | G36: 4931.49 | I36: Total Equity | J36: =C54/C82 -> 0.36450471 | K36: =D54/D82 -> 0.40144017 | L36: =E54/E82 -> 0.38404485 | M36: =F54/F82 -> 0.37226624 | N36: =G54/G82 -> 0.36704672
B37: Trade Receivables | C37: 5915.1 | D37: 5429.36 | E37: 4341.78 | F37: 5651.5 | G37: 6690.07
B38: Cash and Cash Equivalents | C38: 2312.56 | D38: 2240.7 | E38: 2617.04 | F38: 3072.8 | G38: 1223.69
B39: Bank Balances other than Cash and Cash Equivalents | C39: 1400.82 | D39: 1011.85 | E39: 2348.6 | F39: 740.3 | G39: 684.54
B40: Loans | C40: 22342.08 | D40: 14247.01 | E40: 14682.07 | F40: 14175 | G40: 17192.24 | I40: Financial Liabilities | J40: =C58/C82 -> 0.19783946 | K40: =D58/D82 -> 0.16083895 | L40: =E58/E82 -> 0.19654376 | M40: =F58/F82 -> 0.24035234 | N40: =G58/G82 -> 0.2350424
B41: Other Financial Assets | C41: 2348.92 | D41: 2773.76 | E41: 2579.23 | F41: 1697.98 | G41: 1607.19 | J41: =C59/C82 -> 0.0041835971 | K41: =D59/D82 -> 0.0045591001 | L41: =E59/E82 -> 0.0054201303 | M41: =F59/F82 -> 0.0055894095 | N41: =G59/G82 -> 0
J42: =C60/C82 -> 0.19872785 | K42: =D60/D82 -> 0.19940107 | L42: =E60/E82 -> 0.18344914 | M42: =F60/F82 -> 0.15921966 | N42: =G60/G82 -> 0.15619217
B43: Current Tax Assets (Net) | C43: 3.27 | D43: 0.11 | E43: 0.12 | F43: 0.38 | G43: 38.71 | J43: =C61/C82 -> 0.0011819812 | K43: =D61/D82 -> 0.0014815054 | L43: =E61/E82 -> 0.0020385588 | M43: =F61/F82 -> 0.0013712289 | N43: =G61/G82 -> 0.0014460104
B44: Other Current Assets | C44: 3553.27 | D44: 2774.14 | E44: 2404.03 | F44: 2440.34 | G44: 2414.68 | I44: Provisions | J44: =C62/C82 -> 0.0022710515 | K44: =D62/D82 -> 0.0025326645 | L44: =E62/E82 -> 0.001589852 | M44: =F62/F82 -> 0.0012887465 | N44: =G62/G82 -> 0.0010459257
B45: Total Current Assets | C45: 67504.34 | D45: 56758.16 | E45: 57458.55 | I45: Deferred Tax Liabilities | J45: =C63/C82 -> 0.025039306 | K45: =D63/D82 -> 0.029463795 | L45: =E63/E82 -> 0.031666168 | M45: =F63/F82 -> 0.028627691 | N45: =G63/G82 -> 0.036665572
B46: Non-Current Assets/ Disposal Group Held for Sale | C46: 18.02 | D46: 9.53 | E46: 2318.81 | F46: 1077.21 | G46: 1094.73 | I46: Other NCLs | J46: =C64/C82 -> 4.816061e-05 | K46: =D64/D82 -> 0.00026372275 | L46: =E64/E82 -> 0.00049498924 | M46: =F64/F82 -> 0.00051997457 | N46: =G64/G82 -> 0.0003608599
B47: Total Assets | C47: 337205.03 | D47: 289394.83 | E47: 267056.31 | F47: 244415.8 | G47: 241173.93 | I47: Total NCLs | J47: =C65/C82 -> 0.4292914 | K47: =D65/D82 -> 0.39854081 | L47: =E65/E82 -> 0.42120259 | M47: - | N47: -
B48: EQUITY AND LIABILITIES
B49: Equity
B50: Equity Share Capital | C50: 131.69 | D50: 131.67 | E50: 131.62 | F50: 131.57 | G50: 131.53 | I50: Lease Liabilities | J50: =C59/C82 -> 0.0041835971 | K50: =D59/D82 -> 0.0045591001 | L50: =E59/E82 -> 0.0054201303 | M50: =F59/F82 -> 0.0055894095 | N50: =G59/G82 -> 0
B51: Other Equity | C51: 78610.3 | D51: 75566.56 | E51: 65362.44 | F51: 56520.76 | G51: 57887.99
B52: Equity Attributable to Owners of the Company | C52: 78741.99 | D52: 75698.23 | E52: 65494.06 | F52: 56652.33 | G52: 58019.52 | I52: Trade Payables | J52: =C73/C82 -> 0.0010424518 | K52: =D73/D82 -> 0.0008441063 | L52: =E73/E82 -> 0.00056519915 | M52: =F73/F82 -> 0.00034019896 | N52: =G73/G82 -> 0.00015076256
B53: Non-Controlling Interest | C53: 44170.83 | D53: 40476.48 | E53: 37067.54 | F53: 34335.42 | G53: 30502.58 | J53: =C74/C82 -> 0.038557402 | K53: =D74/D82 -> 0.038525775 | L53: =E74/E82 -> 0.029849959 | M53: =F74/F82 -> 0.027025421 | N53: =G74/G82 -> 0.025074601
B54: Total Equity | C54: 122912.82 | D54: 116174.71 | E54: 102561.6 | F54: 90987.75 | G54: 88522.1 | I54: Other FLs | J54: =C75/C82 -> 0.029237435 | K54: =D75/D82 -> 0.028217816 | L54: =E75/E82 -> 0.081058523 | M54: =F75/F82 -> 0.073319892 | N54: =G75/G82 -> 0.059787764
B55: Liabilities | I55: Other CLs | J55: =C76/C82 -> 0.019092687 | K55: =D76/D82 -> 0.022270681 | L55: =E76/E82 -> 0.020922329 | M55: =F76/F82 -> 0.018661069 | N55: =G76/G82 -> 0.01981686
B56: Non-current liabilities | I56: Provisions | J56: =C77/C82 -> 0.0021425244 | K56: =D77/D82 -> 0.0028187788 | L56: =E77/E82 -> 0.0040446526 | M56: =F77/F82 -> 0.0053671653 | N56: =G77/G82 -> 0.0051039099
B57: Financial Liabilities | I57: Current Tax Liabilities | J57: =C78/C82 -> 0.0064258235 | K57: =D78/D82 -> 0.0035162688 | L57: =E78/E82 -> 0.0046552354 | M57: =F78/F82 -> 0.0045918881 | N57: =G78/G82 -> 0.0037491614
B58: Borrowings | C58: 66712.46 | D58: 46545.96 | E58: 52488.25 | F58: 58745.91 | G58: 56686.1 | I58: Total CLs | J58: =C79/C82 -> 0.20620389 | K58: =D79/D82 -> 0.20001902 | L58: =E79/E82 -> 0.19255842 | M58: =F79/F82 -> 0.18876402 | N58: =G79/G82 -> 0.20017275
B59: Lease Liabilities | C59: 1410.73 | D59: 1319.38 | E59: 1447.48 | F59: 1366.14 | I59: Total Liabilities | J59: =C81/C82 -> 0.63549529 | K59: =D81/D82 -> 0.59855983 | L59: =E81/E82 -> 0.61376101 | M59: =F81/F82 -> 0.18876402 | N59: =G81/G82 -> 0.20017275
B60: Policyholder's Liabilities | C60: 67012.03 | D60: 57705.64 | E60: 48991.25 | F60: 38915.8 | G60: 37669.48 | I60: Total Equity and Liabilities | J60: =C82/C82 -> 1 | K60: =D82/D82 -> 1 | L60: =E82/E82 -> 1 | M60: =F82/F82 -> 1 | N60: =G82/G82 -> 1
B61: Other Financial Liabilities | C61: 398.57 | D61: 428.74 | E61: 544.41 | F61: 335.15 | G61: 348.74
B62: Provisions | C62: 765.81 | D62: 732.94 | E62: 424.58 | F62: 314.99 | G62: 252.25
B63: Deferred Tax Liabilities (Net) | C63: 8443.38 | D63: 8526.67 | E63: 8456.65 | F63: 6997.06 | G63: 8842.78
B64: Other Non-current Liabilities | C64: 16.24 | D64: 76.32 | E64: 132.19 | F64: 127.09 | G64: 87.03
B65: Total Non-current liabilities | C65: 144759.22 | D65: 115335.65 | E65: 112484.81
B66: Current Liabilities
B67: Financial Liabilities
B68: Borrowings | C68: 34635.46 | D68: 26457.29 | E68: 10037.04 | F68: 11988.13 | G68: 18378.52
B69: Lease Liabilities | C69: 279.91 | D69: 238.16 | E69: 221.13 | F69: 195.7
B70: Supplier's Credit | D70: 183.4
B71: Policyholder's Liabilities | C71: 2077.9 | D71: 3167.74 | E71: 3485.22 | F71: 2348.74 | G71: 2480.54
B72: Trade Payables
B73: - Total Outstanding dues of Micro and Small Enterprises | C73: 351.52 | D73: 244.28 | E73: 150.94 | F73: 83.15 | G73: 36.36
B74: - Total Outstanding dues of creditors other than Micro and Small Enterprises | C74: 13001.75 | D74: 11149.16 | E74: 7971.62 | F74: 6605.44 | G74: 6047.34
B75: Other Financial Liabilities | C75: 9859.01 | D75: 8166.09 | E75: 21647.19 | F75: 17920.54 | G75: 14419.25
B76: Other Current Liabilities | C76: 6438.15 | D76: 6445.02 | E76: 5587.44 | F76: 4561.06 | G76: 4779.31
B77: Provisions | C77: 722.47 | D77: 815.74 | E77: 1080.15 | F77: 1311.82 | G77: 1230.93
B78: Current Tax Liabilities (Net) | C78: 2166.82 | D78: 1017.59 | E78: 1243.21 | F78: 1122.33 | G78: 904.2
B79: Total Current liabilities | C79: 69532.99 | D79: 57884.47 | E79: 51423.94 | F79: =SUM(F68:F78) -> 46136.91 | G79: =SUM(G68:G78) -> 48276.45
B80: Liabilities directly associated with Non-Current Assets Held for Sale | E80: 585.96 | F80: 489 | G80: 489
B81: Total Liabilities | C81: =C65+C79 -> 214292.21 | D81: =D65+D79 -> 173220.12 | E81: =E65+E79 -> 163908.75 | F81: =F65+F79 -> 46136.91 | G81: =G65+G79 -> 48276.45
B82: Total Equity and Liabilities | C82: 337205.03 | D82: 289394.83 | E82: 267056.31 | F82: 244415.8 | G82: 241173.93
B87: No. of Equity Shares (in Crores) | C87: 65.84 | D87: 65.84 | E87: 65.84 | F87: 65.84 | G87: 65.84
B88: MPS (INR) | C88: 1632.7 | D88: 1664 | E88: 1450.55 | F88: 476.1 | G88: 830.15
B89: Value per Share (Book Value) | C89: =C54/C87 -> 1866.8411 | D89: =D54/D87 -> 1764.5005 | E89: =E54/E87 -> 1557.74 | F89: =F54/F87 -> 1381.9525 | G89: =G54/G87 -> 1344.5033
B90: Price to Book Value (P/BV) Ratio
B111: MPS (INR) as of Sept 1, 2023 (Rs)
B113: Price to Book Value (P/BV) Ratio as of Sep 1, 2023
B115: Tangible Value of the Firm (Total Equity - Intangible Assets)
B117: Tangible Value per Share (Tangible Value / No. of Equity Shares)
B120: Ex: Calculation of Liquidation Value:
B121: Realisable Value of the Assets
B122: Total Liabilities (Non CL + CL)
B123: Liquidation Value (Realisable value of the assets -Total Liabilities)
B124: Liquidation value per share (Liquidation value/ no. of equity shares)
B127: Liquidity Position (TCA/TCL)
B128: Total Current Assets/ Total Current Liabilities)

Sheet Vertical Analysis of P&L
B2: Table 2.1: Statement of Profit and Loss of Grasim Industries Ltd. (India) | I2: Vertical (Common Size) Analysis of Statement of Profit and Loss | Q2: Table 2.2: Statement of Profit and Loss & its contents | X2: Table 2.3: Analysis of Satement of Profit and Loss
B3: for the year ended (₹ in Crores) | I3: (Each item as a % of Revenue from Operations) | Q3: Particulars | R3: March 31, 2023 | S3: March 31, 2022 | T3: March 31, 2021 | U3: March 31, 2020 | V3: March 31, 2019 | X3: Particulars | Y3: March 31, 2023 | Z3: March 31, 2022 | AA3: March 31, 2021 | AB3: March 31, 2020 | AC3: March 31, 2019
B4: Particulars | C4: March 31, 2023 | D4: March 31, 2022 | E4: March 31, 2021 | F4: March 31, 2020 | G4: March 31, 2019 | J4: March 31, 2023 | K4: March 31, 2022 | L4: March 31, 2021 | M4: March 31, 2020 | N4: March 31, 2019 | X4: Growth in Revenue from Operations | Y4: ='Statement of P & L'!R4 -> 0.22910858 | Z4: ='Statement of P & L'!S4 -> 0.2526685 | AA4: ='Statement of P & L'!T4 -> -0.015810479 | AB4: ='Statement of P & L'!U4 -> 0.0055032205 | AC4: ='Statement of P & L'!V4 -> 0
B5: Revenue from operations | C5: 117627.08 | D5: 95701.13 | E5: 76397.81 | F5: 77625.1 | G5: 77200.25 | I5: Revenue from operations | J5: =(C5/$C$5)*100 -> 100 | K5: =(D5/$D$5)*100 -> 100 | L5: =(E5/$E$5)*100 -> 100 | M5: =(F5/$F$5)*100 -> 100 | N5: =(G5/$G$5)*100 -> 100 | Q5: Revenue from operations (% of Total Income) | R5: ='Statement of P & L'!K5 -> 0.97020723 | S5: ='Statement of P & L'!L5 -> 0.99149069 | T5: ='Statement of P & L'!M5 -> 0.98641752 | U5: ='Statement of P & L'!N5 -> 0.98770087 | V5: ='Statement of P & L'!O5 -> 0.98939239
B6: Other Income | C6: 3612.05 | D6: 821.34 | E6: 1051.96 | F6: 966.61 | G6: 827.69 | I6: Other Income | J6: =(C6/$C$5)*100 -> 3.070764 | K6: =(D6/$D$5)*100 -> 0.85823438 | L6: =(E6/$E$5)*100 -> 1.3769505 | M6: =(F6/$F$5)*100 -> 1.2452287 | N6: =(G6/$G$5)*100 -> 1.0721338 | Q6: Other income (% of Total Income) | R6: ='Statement of P & L'!K6 -> 0.029792774 | S6: ='Statement of P & L'!L6 -> 0.0085093139 | T6: ='Statement of P & L'!M6 -> 0.013582481 | U6: ='Statement of P & L'!N6 -> 0.012299134 | V6: ='Statement of P & L'!O6 -> 0.010607611
B7: Total Income (I) | C7: 121239.13 | D7: 96522.47 | E7: 77449.77 | F7: 78591.71 | G7: 78027.94 | I7: Total Income (I) | J7: =(C7/$C$5)*100 -> 103.07076 | K7: =(D7/$D$5)*100 -> 100.85823 | L7: =(E7/$E$5)*100 -> 101.37695 | M7: =(F7/$F$5)*100 -> 101.24523 | N7: =(G7/$G$5)*100 -> 101.07213 | X7: Growth in Net Income (PAT) | Y7: ='Statement of P & L'!R7 -> 0.036260997 | Z7: ='Statement of P & L'!S7 -> 0.58396353 | AA7: ='Statement of P & L'!T7 -> 0.010746569 | AB7: ='Statement of P & L'!U7 -> 1.4328279 | AC7: ='Statement of P & L'!V7 -> 0
B8: Expenses | I8: Expenses | L8: =(E8/$E$5)*100 -> 0 | M8: =(F8/$F$5)*100 -> 0 | N8: =(G8/$G$5)*100 -> 0
B9: Cost of materials consumed | C9: 21622.26 | D9: 16889.6 | E9: 11006.75 | F9: 14618.05 | G9: 15261.12 | I9: Cost of materials consumed | J9: =(C9/$C$5)*100 -> 18.382043 | K9: =(D9/$D$5)*100 -> 17.648276 | L9: =(E9/$E$5)*100 -> 14.407154 | M9: =(F9/$F$5)*100 -> 18.831602 | N9: =(G9/$G$5)*100 -> 19.768226 | Q9: Material Expenses (% of Revenue from Operations) | R9: ='Statement of P & L'!K9 -> 0.20642585 | S9: ='Statement of P & L'!L9 -> 0.20079073 | T9: ='Statement of P & L'!M9 -> 0.16530867 | U9: ='Statement of P & L'!N9 -> 0.21402626 | V9: ='Statement of P & L'!O9 -> 0.21823789 | X9: Operating Profit (EBIT) | Y9: ='Statement of P & L'!R9 -> 219536.97 | Z9: ='Statement of P & L'!S9 -> 176427.66 | AA9: ='Statement of P & L'!T9 -> 140009.04 | AB9: ='Statement of P & L'!U9 -> 144162.28 | AC9: ='Statement of P & L'!V9 -> 143355.21
B10: Purchases of stock-in-trade | C10: 1824.35 | D10: 1404.56 | E10: 898.44 | F10: 1469.86 | G10: 1507.01 | I10: Purchases of stock-in-trade | J10: =(C10/$C$5)*100 -> 1.5509609 | K10: =(D10/$D$5)*100 -> 1.4676525 | L10: =(E10/$E$5)*100 -> 1.1760023 | M10: =(F10/$F$5)*100 -> 1.893537 | N10: =(G10/$G$5)*100 -> 1.9520792
B11: Changes in inventories of finished goods, work-in-progress and stock-in-trade | C11: 834.66 | D11: 921.74 | E11: 724.03 | F11: 525.9 | G11: 79.89 | I11: Changes in inventories of finished goods, work-in-progress and stock-in-trade | J11: =(C11/$C$5)*100 -> 0.7095815 | K11: =(D11/$D$5)*100 -> 0.96314432 | L11: =(E11/$E$5)*100 -> 0.94771041 | M11: =(F11/$F$5)*100 -> 0.67748705 | N11: =(G11/$G$5)*100 -> 0.10348412 | X11: Operating Profit Margin (EBIT/ Revenue from Operations) | Y11: ='Statement of P & L'!R11 -> 1.8663812 | Z11: ='Statement of P & L'!S11 -> 1.8435274 | AA11: ='Statement of P & L'!T11 -> 1.8326316 | AB11: ='Statement of P & L'!U11 -> 1.8571606 | AC11: ='Statement of P & L'!V11 -> 1.8569268
B12: Employee benefits expense | C12: 7193.86 | D12: 6327.71 | E12: 5534.74 | F12: 5864.53 | G12: 5428.21 | I12: Employee benefits expense | J12: =(C12/$C$5)*100 -> 6.1158196 | K12: =(D12/$D$5)*100 -> 6.6119491 | L12: =(E12/$E$5)*100 -> 7.2446318 | M12: =(F12/$F$5)*100 -> 7.5549403 | N12: =(G12/$G$5)*100 -> 7.0313373 | Q12: Employee benefit Exp. (% of Revenue from Operations) | R12: ='Statement of P & L'!K12 -> 0.061158196 | S12: ='Statement of P & L'!L12 -> 0.066119491 | T12: ='Statement of P & L'!M12 -> 0.072446318 | U12: ='Statement of P & L'!N12 -> 0.075549403 | V12: ='Statement of P & L'!O12 -> 0.070313373
B13: Power and Fuel | C13: 23168.73 | D13: 15520.7 | E13: 10363.78 | F13: 11436.68 | G13: 12423.45 | I13: Power and Fuel | J13: =(C13/$C$5)*100 -> 19.696765 | K13: =(D13/$D$5)*100 -> 16.217886 | L13: =(E13/$E$5)*100 -> 13.565546 | M13: =(F13/$F$5)*100 -> 14.733224 | N13: =(G13/$G$5)*100 -> 16.0925
B14: Freight and Handling Expenses | C14: 15024.93 | D14: 12584.1 | E14: 10381.83 | F14: 10058.06 | G14: 10619.15 | I14: Freight and Handling Expenses | J14: =(C14/$C$5)*100 -> 12.77336 | K14: =(D14/$D$5)*100 -> 13.149375 | L14: =(E14/$E$5)*100 -> 13.589172 | M14: =(F14/$F$5)*100 -> 12.957226 | N14: =(G14/$G$5)*100 -> 13.755331
B15: Change in Valuation of Liability in respect of Insurance Policies | C15: 7451.57 | D15: 4240.83 | E15: 4374.84 | F15: 1032.26 | G15: 1408.88 | I15: Change in Valuation of Liability in respect of Insurance Policies | J15: =(C15/$C$5)*100 -> 6.3349103 | K15: =(D15/$D$5)*100 -> 4.431327 | L15: =(E15/$E$5)*100 -> 5.7263945 | M15: =(F15/$F$5)*100 -> 1.3298018 | N15: =(G15/$G$5)*100 -> 1.8249682
B16: Benefits Paid - Insurance Business | C16: 5467.75 | D16: 6702.55 | E16: 4445.05 | F16: 5177.01 | G16: 4553.57 | I16: Benefits Paid - Insurance Business | J16: =(C16/$C$5)*100 -> 4.6483769 | K16: =(D16/$D$5)*100 -> 7.0036268 | L16: =(E16/$E$5)*100 -> 5.8182951 | M16: =(F16/$F$5)*100 -> 6.6692474 | N16: =(G16/$G$5)*100 -> 5.8983876
B17: Finance Cost relating to NBFC/HFC's Business | C17: 4723.46 | D17: 3480.3 | E17: 3914.6 | F17: 4587.82 | G17: 4050.18 | I17: Finance Cost relating to NBFC/HFC's Business | J17: =(C17/$C$5)*100 -> 4.0156229 | K17: =(D17/$D$5)*100 -> 3.6366342 | L17: =(E17/$E$5)*100 -> 5.1239689 | M17: =(F17/$F$5)*100 -> 5.9102275 | N17: =(G17/$G$5)*100 -> 5.2463302 | Q17: Finance Exp. (% of Revenue from Operations) | R17: ='Statement of P & L'!K17 -> 0.040156229 | S17: ='Statement of P & L'!L17 -> 0.036366342 | T17: ='Statement of P & L'!M17 -> 0.051239689 | U17: ='Statement of P & L'!N17 -> 0.059102275 | V17: ='Statement of P & L'!O17 -> 0.052463302
B18: Other Finance Costs | C18: 1320.27 | D18: 1295.7 | E18: 1808.88 | F18: 2338.5 | G18: 2009.85 | I18: Other Finance Costs | J18: =(C18/$C$5)*100 -> 1.1224201 | K18: =(D18/$D$5)*100 -> 1.3539025 | L18: =(E18/$E$5)*100 -> 2.3677118 | M18: =(F18/$F$5)*100 -> 3.0125565 | N18: =(G18/$G$5)*100 -> 2.6034242
B19: Depreciation and Amortisation expense | C19: 4551.59 | D19: 4161.07 | E19: 4033.4 | F19: 4040.82 | G19: 3571.38 | I19: Depreciation and Amortisation expense | J19: =(C19/$C$5)*100 -> 3.8695086 | K19: =(D19/$D$5)*100 -> 4.3479842 | L19: =(E19/$E$5)*100 -> 5.2794707 | M19: =(F19/$F$5)*100 -> 5.2055585 | N19: =(G19/$G$5)*100 -> 4.6261249 | Q19: D & A Exp. (% of Revenue from Operations) | R19: ='Statement of P & L'!K19 -> 0.038695086 | S19: ='Statement of P & L'!L19 -> 0.043479842 | T19: ='Statement of P & L'!M19 -> 0.052794707 | U19: ='Statement of P & L'!N19 -> 0.052055585 | V19: ='Statement of P & L'!O19 -> 0.046261249 | X19: EBITDA (EBIT+ D&A) | Y19: ='Statement of P & L'!R19 -> 224088.56 | Z19: ='Statement of P & L'!S19 -> 180588.73 | AA19: ='Statement of P & L'!T19 -> 144042.44 | AB19: ='Statement of P & L'!U19 -> 148203.1 | AC19: ='Statement of P & L'!V19 -> 146926.59
B20: Other Expenses | C20: 15119.24 | D20: 12521.45 | E20: 10069.97 | F20: 11047.77 | G20: 9482.99 | I20: Other Expenses | J20: =(C20/$C$5)*100 -> 12.853537 | K20: =(D20/$D$5)*100 -> 13.08391 | L20: =(E20/$D$5)*100 -> 10.52231 | M20: =(F20/$D$5)*100 -> 11.544033 | N20: =(G20/$G$5)*100 -> 12.283626 | Q20: Other Exp (% of Revenue from Operations) | R20: ='Statement of P & L'!K20 -> 0.12853537 | S20: ='Statement of P & L'!L20 -> 0.1308391 | T20: ='Statement of P & L'!M20 -> 0.13180967 | U20: ='Statement of P & L'!N20 -> 0.14232214 | V20: ='Statement of P & L'!O20 -> 0.12283626 | X20: EBITDA Margin | Y20: ='Statement of P & L'!R20 -> 1.9050763 | Z20: ='Statement of P & L'!S20 -> 1.8870073 | AA20: ='Statement of P & L'!T20 -> 1.8854263 | AB20: ='Statement of P & L'!U20 -> 1.9092162 | AC20: ='Statement of P & L'!V20 -> 1.903188
B21: Total Expenses (II) | C21: 106633.35 | D21: 84206.83 | E21: 67525.83 | F21: 71125 | G21: 70205.14 | I21: Total Expenses (II) | J21: =(C21/$C$5)*100 -> 90.653742 | K21: =(D21/$D$5)*100 -> 87.989379 | L21: =(E21/$E$5)*100 -> 88.387128 | M21: =(F21/$F$5)*100 -> 91.626291 | N21: =(G21/$G$5)*100 -> 90.939006 | Q21: Total Expenses (% of Revenue from Operations) | R21: ='Statement of P & L'!K21 -> 0.90653742 | S21: ='Statement of P & L'!L21 -> 0.87989379 | T21: ='Statement of P & L'!M21 -> 0.88387128 | U21: ='Statement of P & L'!N21 -> 0.91626291 | V21: ='Statement of P & L'!O21 -> 0.90939006
I22: Current Tax | J22: =(C31/$C$5)*100 -> 2.9182651 | K22: =(D31/$D$5)*100 -> 2.0421911 | L22: =(E31/$E$5)*100 -> 2.5647332 | M22: =(F31/$F$5)*100 -> 2.0706962 | N22: =(G31/$G$5)*100 -> 3.0303011 | X22: Other income (% of PAT) | Y22: ='Statement of P & L'!R22 -> 0.32605026 | Z22: ='Statement of P & L'!S22 -> 0.076828601 | AA22: ='Statement of P & L'!T22 -> 0.15586347 | AB22: ='Statement of P & L'!U22 -> 0.1447567 | AC22: ='Statement of P & L'!V22 -> 0.30155497
B23: Profit from Continuing Operations Before Share in Profit of (I - II) | C23: 14605.78 | D23: 12315.64 | E23: 9923.94 | F23: 7466.71 | G23: 7822.8 | I23: Deferred Tax | J23: =(C32/$C$5)*100 -> 0.18349516 | K23: =(D32/$D$5)*100 -> 0.018902598 | L23: =(E32/$E$5)*100 -> 1.3911263 | M23: =(F32/$F$5)*100 -> 2.1044611 | N23: =(G32/$G$5)*100 -> 0.12283639
B24: Equity Accounted Investees, Exceptional Items and Tax | I24: Total Tax Expenses | J24: =(C33/$C$5)*100 -> 3.1017602 | K24: =(D33/$D$5)*100 -> 2.0232885 | L24: =(E33/$E$5)*100 -> 3.9558595 | M24: =(F33/$F$5)*100 -> 0.039484651 | N24: =(G33/$G$5)*100 -> 3.1330468
B25: Share in Profit of Equity Accounted Investees | C25: 208.96 | D25: 380.33 | E25: 189.22 | I25: Profit for the year (III) (PAT) | J25: =(C34/$C$5)*100 -> 9.4180694 | K25: =(D34/$D$5)*100 -> 11.170767 | L25: =(E34/$E$5)*100 -> 8.834337 | M25: =(F34/$F$5)*100 -> 8.6022176 | N25: =(G34/$G$5)*100 -> 3.5553512
B26: Profit from Continuing Operations Before Tax and Exceptional Items | C26: 14814.74 | D26: 12695.97 | E26: 10113.16 | I26: Other Comprehensive Income (net of Tax) | X26: Avg Assets (Current year Assets + Previous Year Assets)/2 | Y26: ='Statement of P & L'!R26 -> 313299.93 | Z26: ='Statement of P & L'!S26 -> 278225.57 | AA26: ='Statement of P & L'!T26 -> 255736.05 | AB26: ='Statement of P & L'!U26 -> 242794.86 | AC26: ='Statement of P & L'!V26 -> 120586.96
B27: Exceptional Items | C27: 88.03 | D27: 69.11 | E27: 341.73 | I27: Items that will not be reclassified to Profit and Loss | J27: =(C43/$C$5)*100 -> 2.9281353 | K27: =(D43/$D$5)*100 -> 3.5967809 | L27: =(E43/$E$5)*100 -> 9.1451574 | M27: =(F43/$F$5)*100 -> 7.1010408 | N27: =(G43/$G$5)*100 -> 3.4837322 | Q27: PBT (% OF Revenue from Operations) | R27: ='Statement of P & L'!K27 -> 0.1251983 | S27: ='Statement of P & L'!L27 -> 0.13194055 | T27: ='Statement of P & L'!M27 -> 0.12790196 | U27: ='Statement of P & L'!N27 -> 0.0072427604 | V27: ='Statement of P & L'!O27 -> 0.00037642365 | X27: ROI (PAT/Avg. Assets) | Y27: ='Statement of P & L'!R27 -> 0.035359727 | Z27: ='Statement of P & L'!S27 -> 0.038424038 | AA27: ='Statement of P & L'!T27 -> 0.026391429 | AB27: ='Statement of P & L'!U27 -> 0.027502559 | AC27: ='Statement of P & L'!V27 -> 0.022761498
B28: Profit from Continuing Operations Before Tax (PBT) | C28: 14726.71 | D28: 12626.86 | E28: 9771.43 | F28: 562.22 | G28: 29.06 | I28: Income Tax relating to items that will not be reclassified to Profit or Loss | J28: =(C44/$C$5)*100 -> 0.32972849 | K28: =(D44/$C$5)*100 -> 0.18853652 | L28: =(E44/$C$5)*100 -> 0.32906538 | M28: =(F44/$C$5)*100 -> 0.31763094 | N28: =(G44/$C$5)*100 -> 0.026405484 | X28: Average Equity | Y28: ='Statement of P & L'!R28 -> 119543.77 | Z28: ='Statement of P & L'!S28 -> 109368.15 | AA28: ='Statement of P & L'!T28 -> 96774.675 | AB28: ='Statement of P & L'!U28 -> 89754.925 | AC28: ='Statement of P & L'!V28 -> 44261.05
B29: Tax expense | I29: Items that will be reclassified to Profit or Loss | J29: =(C45/$C$5)*100 -> 0.15476028 | K29: =(D45/$D$5)*100 -> 0.066749473 | L29: =(E45/$E$5)*100 -> 0.21405064 | M29: =(F45/$F$5)*100 -> 0.18747802 | N29: =(G45/$G$5)*100 -> 0.10023284
B30: Tax Expense of Continuing Operations (Net) | I30: Income Tax relating to items that will be reclassified to Profit or Loss | J30: =(C46/$C$5)*100 -> 0.049044829 | K30: =(D46/$D$5)*100 -> 0.0036258715 | L30: =(E46/$E$5)*100 -> 0.024542588 | M30: =(F46/$F$5)*100 -> 0.011542658 | N30: =(G46/$G$5)*100 -> 0.021541381 | X30: ROE (PAT/Avg Equity) | Y30: ='Statement of P & L'!R30 -> 0.092670663 | Z30: ='Statement of P & L'!S30 -> 0.097748289 | AA30: ='Statement of P & L'!T30 -> 0.0697418 | AB30: ='Statement of P & L'!U30 -> 0.074396809 | AC30: ='Statement of P & L'!V30 -> 0.062012537
B31: Current Tax | C31: 3432.67 | D31: 1954.4 | E31: 1959.4 | F31: 1607.38 | G31: 2339.4 | I31: Total comprehensive income for the period | J31: =(C48/$C$5)*100 -> 6.7139472 | K31: =(D48/$D$5)*100 -> 15.137846 | L31: =(E48/$E$5)*100 -> 15.481622 | M31: =(F48/$F$5)*100 -> 2.1584256 | N31: =(G48/$G$5)*100 -> 0.047305546
B32: Deferred Tax | C32: 215.84 | D32: 18.09 | E32: 1062.79 | F32: 1633.59 | G32: 94.83 | I32: Earnings Per Equity Share attributable to the Owners of the Company | J32: =(C66/$C$5)*100 -> 0.088398012 | K32: =(D66/$D$5)*100 -> 0.11301852 | L32: =(E66/$E$5)*100 -> 0.082306024 | M32: =(F66/$F$5)*100 -> 0.08685335 | N32: =(G66/$G$5)*100 -> 0.033367768 | Q32: Total Tax Exp. (% of Revenue from Operations) | R32: ='Statement of P & L'!K32 -> 0.031017602 | S32: ='Statement of P & L'!L32 -> 0.020232885 | T32: ='Statement of P & L'!M32 -> 0.039558595 | U32: ='Statement of P & L'!N32 -> 0.00039484651 | V32: ='Statement of P & L'!O32 -> 0.031330468 | X32: P/E (Price to Earnings) Ratio (MPS/EPS) | Y32: ='Statement of P & L'!R32 -> 15.702058 | Z32: ='Statement of P & L'!S32 -> 14.472082 | AA32: ='Statement of P & L'!T32 -> 22.12216 | AB32: ='Statement of P & L'!U32 -> 7.0617028 | AC32: ='Statement of P & L'!V32 -> 32.22632
B33: Total Tax Expenses | C33: 3648.51 | D33: 1936.31 | E33: 3022.19 | F33: 30.65 | G33: 2418.72 | I33: Basic and Diluted EPS (of Re 1/- each) (INR) | Q33: PAT (% of Revenue from Operations) | R33: ='Statement of P & L'!K33 -> 0.094180694 | S33: ='Statement of P & L'!L33 -> 0.11170767 | T33: ='Statement of P & L'!M33 -> 0.08834337 | U33: ='Statement of P & L'!N33 -> 0.086022176 | V33: ='Statement of P & L'!O33 -> 0.035553512 | X33: P/S (Price to Sales) Ratio (MPS/Sales per Share) | Y33: ='Statement of P & L'!R33 -> 0.91387942 | Z33: ='Statement of P & L'!S33 -> 1.1447907 | AA33: ='Statement of P & L'!T33 -> 1.250091 | AB33: ='Statement of P & L'!U33 -> 0.40381815 | AC33: ='Statement of P & L'!V33 -> 0.70799092
B34: Profit for the Year from Continuing Operations (III) (PAT) | C34: 11078.2 | D34: 10690.55 | E34: 6749.24 | F34: 6677.48 | G34: 2744.74 | I34: Significant Accounting Policies
B35: Discontinued Operations | I35: The accompanying notes are an integral part of these financial statements.
B36: Profit Before Tax from Discontinued Operations | D36: 352.52 | E36: 162.79 | F36: 90.03 | G36: 54.94
B37: Exceptional Items | D37: 670.71 | E37: 166.5 | F37: 36.63 | G37: 15.31
B38: Tax Expenses of Discontinued Operations | D38: 440.07 | E38: 66.1
B39: Less: Reversal / (Provision) of Impairment of Assets Classified as Held for Sale | D39: 67.42 | E39: 25.73 | F39: 53.4 | G39: 39.63
B40: Profit for the Year from Discontinued Operations (IV) | D40: 515.74 | E40: 237.46
B41: Profit for the Year (V = III + IV) | C41: 11078.2 | D41: 11206.29 | E41: 6986.7 | F41: 6677.48 | G41: 2744.74 | Q41: PBIT (PBT+ Finance Cost) | R41: ='Statement of P & L'!K41 -> 19450.17 | S41: ='Statement of P & L'!L41 -> 16107.16 | T41: ='Statement of P & L'!M41 -> 13686.03 | U41: ='Statement of P & L'!N41 -> 5150.04 | V41: ='Statement of P & L'!O41 -> 4079.24
B42: Other Comprehensive Income (net of Tax) | Q42: PBIT (% of Revenue from Operations) | R42: ='Statement of P & L'!K42 -> 0.16535453 | S42: ='Statement of P & L'!L42 -> 0.16830689 | T42: ='Statement of P & L'!M42 -> 0.17914165 | U42: ='Statement of P & L'!N42 -> 0.066345035 | V42: ='Statement of P & L'!O42 -> 0.052839725 | X42: Sales per Share (Revenue from Operations/No. of Equity shares) | Y42: ='Statement of P & L'!R42 -> 1786.5595 | Z42: ='Statement of P & L'!S42 -> 1453.5409 | AA42: ='Statement of P & L'!T42 -> 1160.3556 | AB42: ='Statement of P & L'!U42 -> 1178.9961 | AC42: ='Statement of P & L'!V42 -> 1172.5433
B43: A (i) Items that will not be reclassified to Profit or Loss | C43: 3444.28 | D43: 3442.16 | E43: 6986.7 | F43: 5512.19 | G43: 2689.45
B44: (ii) Income Tax relating to items that will not be reclassified to Profit or Loss | C44: 387.85 | D44: 221.77 | E44: 387.07 | F44: 373.62 | G44: 31.06
B45: B (i) Items that will be reclassified to Profit or Loss | C45: 182.04 | D45: 63.88 | E45: 163.53 | F45: 145.53 | G45: 77.38
B46: (ii) Income Tax relating to items that will be reclassified to Profit or Loss | C46: 57.69 | D46: 3.47 | E46: 18.75 | F46: 8.96 | G46: 16.63
B47: Other Comprehensive Income for the Year (VI) | C47: 3180.78 | D47: 3280.8 | E47: 4840.92 | F47: 5002 | G47: 2781.26
B48: Total comprehensive income for the Year (V+VI) | C48: 7897.42 | D48: 14487.09 | E48: 11827.62 | F48: 1675.48 | G48: 36.52
B49: Profit from Continuing Operations Attributable to:
B50: Owners of the Company | C50: 6827.26 | D50: 7102.37 | E50: 4128.41 | F50: 4425.19 | G50: 1692.99
B51: Non-Controlling Interest | C51: 4250.94 | D51: 3588.18 | E51: 2620.83 | F51: 2252.29 | G51: 1051.75
C52: 11078.2 | D52: 10690.55 | E52: 6749.24 | F52: 6677.48 | G52: 2744.74
B53: Profit Attributable to:
B54: Owners of the Company | C54: 6827.26 | D54: 7549.78 | E54: 4304.82 | F54: 4425.19 | G54: 1692.99
B55: Non-Controlling Interest | C55: 4250.94 | D55: 3656.51 | E55: 2681.88 | F55: 2252.29 | G55: 1051.75
C56: 11078.2 | D56: 11206.29 | E56: 6986.7 | F56: 6677.48 | G56: 2744.74
B57: Other Comprehensive Income Attributable to:
B58: Owners of the Company | C58: 3104.23 | D58: 3281.85 | E58: 4780.54 | F58: 5067.74 | G58: 2822.5
B59: Non-Controlling Interest | C59: 76.55 | D59: 1.05 | E59: 60.38 | F59: 65.74 | G59: 41.24
C60: 3180.78 | D60: 3280.8 | E60: 4840.92 | F60: 5002 | G60: 2781.26
B61: Total Comprehensive Income Attributable to:
B62: Owners of the Company | C62: 3723.03 | D62: 10831.63 | E62: 9085.36 | F62: 642.55 | G62: 1129.51
B63: Non-Controlling Interest | C63: 4174.39 | D63: 3655.46 | E63: 2742.26 | F63: 2318.03 | G63: 1092.99
C64: 7897.42 | D64: 14487.09 | E64: 11827.62 | F64: 1675.48 | G64: 36.52
B65: Earnings Per Equity Share (Face Value D 2 each) - Continuing Operations
B66: Basic (₹) | C66: 103.98 | D66: 108.16 | E66: 62.88 | F66: 67.42 | G66: 25.76
B67: Diluted (₹) | C67: 103.88 | D67: 108 | E67: 62.82 | F67: 67.38 | G67: 25.74
B68: Earnings Per Equity Share (Face Value D 2 each) - Discontinued Operations
B69: Basic (₹) | D69: 6.82 | E69: 2.69
B70: Diluted (₹) | D70: 6.8 | E70: 2.68
B71: Earnings Per Equity Share (Face Value D 2 each) - Continuing and Discontinued Operations
B72: Basic (₹) | C72: 103.98 | D72: 114.98 | E72: 65.57 | F72: 67.42 | G72: 25.76
B73: Diluted (₹) | C73: 103.88 | D73: 114.8 | E73: 65.5 | F73: 67.38 | G73: 25.74

Sheet Horizontal Analysis of BS
B2: Table 1.1: Balance Sheet of GRASIM INDUSTRIES LTD (India) | I2: Horizontal (Comparative) Analysis of Balance Sheet
B3: (₹ in Crores) | I3: (Base Year March, 2019) Each item as a % of its March 2019 amount)
B4: Particulars | C4: As at March 31, 2023 | D4: As at March 31, 2022 | E4: As at March 31, 2021 | F4: As at March 31, 2020 | G4: As at March 31, 2019 | J4: As at March 31, 2023 | K4: As at March 31, 2022 | L4: As at March 31, 2021 | M4: As at March 31, 2020 | N4: As at March 31, 2019
B5: ASSETS
B6: Non-Current Assets
B7: Property, Plant and Equipment | C7: 63753.53 | D7: 58148.57 | E7: 53767.33 | F7: 55758.44 | G7: 55652.22 | I7: PPE | J7: =(C7/$G$7)*100 -> 114.55703 | K7: =(D7/$G$7)*100 -> 104.48563 | L7: =(E7/$G$7)*100 -> 96.613091 | M7: =(F7/$G$7)*100 -> 100.19086 | N7: =(G7/$G$7)*100 -> 100
B8: Capital Work-in-progress | C8: 7730.18 | D8: 6572.18 | E8: 5719.43 | F8: 3822.45 | G8: 2728.2 | I8: Capital WIP | J8: =(C8/$G$8)*100 -> 283.3436 | K8: =(D8/$G$8)*100 -> 240.89803 | L8: =(E8/$G$8)*100 -> 209.64116 | M8: =(F8/$G$8)*100 -> 140.10886 | N8: =(G8/$G$8)*100 -> 100
B9: Investment Property | C9: 14.37 | D9: 14.81 | E9: 15.24 | F9: 15.67 | G9: 16.11 | I9: Intangible Assets
B10: Goodwill | C10: 20137.55 | D10: 20058.5 | E10: 20013.86 | F10: 20046.5 | G10: 21346.39
B11: Other Intangible Assets | C11: 8591.89 | D11: 8895.41 | E11: 9254.48 | F11: 9684.29 | G11: 10114.47 | I11: Financial Assets | J11: =(C20/$G$20)*100 -> 253.33307 | K11: =(D20/$G$20)*100 -> 198.39694 | L11: =(E20/$G$20)*100 -> 160.5409 | M11: =(F20/$G$20)*100 -> 123.51056 | N11: =(G20/$G$20)*100 -> 100
J12: =(C21/$G$21)*100 -> 108.58943 | K12: =(D21/$G$21)*100 -> 158.61983 | L12: =(E21/$G$21)*100 -> 121.04164 | M12: =(F21/$G$21)*100 -> 70.980618 | N12: =(G21/$G$21)*100 -> 100
J13: =(C22/$G$22)*100 -> 132.65702 | K13: =(D22/$G$22)*100 -> 129.16987 | L13: =(E22/$G$22)*100 -> 114.90671 | M13: =(F22/$G$22)*100 -> 87.170451 | N13: =(G22/$G$22)*100 -> 100
J14: - | K14: - | L14: - | M14: - | N14: -
B15: Intangible Assets under Development | C15: 47.5 | D15: 42.94 | E15: 49.26 | F15: 81.68 | G15: 37.77 | J15: =(C24/$G$24)*100 -> 152.78996 | K15: =(D24/$G$24)*100 -> 112.00709 | L15: =(E24/$G$24)*100 -> 98.61825 | M15: =(F24/$G$24)*100 -> 99.289032 | N15: =(G24/$G$24)*100 -> 100
B16: Right of Use Assets | C16: 2399.03 | D16: 1878.83 | E16: 1971.89 | F16: 2062.63 | J16: =(C25/$G$25)*100 -> 1178.9589 | K16: =(D25/$G$25)*100 -> 770.77454 | L16: =(E25/$G$25)*100 -> 398.03387 | M16: =(F25/$G$25)*100 -> 162.44277 | N16: =(G25/$G$25)*100 -> 100
B17: Investment in Equity Accounted Investees | C17: 11016.84 | D17: 7050.17 | E17: 6837.66 | F17: 6533.09 | G17: 6284.29
B18: Financial Assets | I18: Other NCAs
B19: Investments | I19: Current Tax Assets | J19: =(C43/$G$43)*100 -> 8.4474296 | K19: =(D43/$G$43)*100 -> 0.2841643 | L19: =(E43/$G$43)*100 -> 0.30999742 | M19: =(F43/$G$43)*100 -> 0.98165849 | N19: =(G43/$G$43)*100 -> 100
B20: Investments of Insurance Business | C20: 39523.43 | D20: 30952.64 | E20: 25046.58 | F20: 19269.34 | G20: 15601.37 | I20: Total Non-CAs | J20: =(C29/$G$29)*100 -> 140.97858 | K20: =(D29/$G$29)*100 -> 121.60754 | L20: =(E29/$G$29)*100 -> 108.35658 | M20: =(F29/$G$29)*100 -> 100.40623 | N20: =(G29/$G$29)*100 -> 100
B21: Other Investments | C21: 9502.9 | D21: 13881.17 | E21: 10592.62 | F21: 6211.67 | G21: 8751.22
B22: Asset Held to Cover Linked Liabilities of Life Insurance Business | C22: 26842.95 | D22: 26137.33 | E22: 23251.2 | F22: 17638.81 | G22: 20234.85 | I22: Inventories | J22: =(C31/$G$31)*100 -> 158.08109 | K22: =(D31/$G$31)*100 -> 135.09342 | L22: =(E31/$G$31)*100 -> 87.786455 | M22: =(F31/$G$31)*100 -> 96.408056 | N22: =(G31/$G$31)*100 -> 100
B23: Trade Receivables | C23: 6.82
B24: Loans | C24: 70871.12 | D24: 51954.12 | E24: 45743.75 | F24: 46054.89 | G24: 46384.67 | I24: A/c Receivables | J24: - | K24: - | L24: - | M24: - | N24: -
B25: Other Financial Assets | C25: 3759.7 | D25: 2458 | E25: 1269.33 | F25: 518.03 | G25: 318.9 | I25: Cash & Bank Balances | J25: =(C38/$G$38)*100 -> 188.9825 | K25: =(D38/$G$38)*100 -> 183.1101 | L25: =(E38/$G$38)*100 -> 213.86462 | M25: =(F38/$G$38)*100 -> 251.10935 | N25: =(G38/$G$38)*100 -> 100
B26: Deferred Tax Assets (Net) | C26: 382.26 | D26: 246.04 | E26: 205.44 | F26: 137.57 | G26: 46.95 | J26: =(C39/$G$39)*100 -> 204.63669 | K26: =(D39/$G$39)*100 -> 147.81459 | L26: =(E39/$G$39)*100 -> 343.09171 | M26: =(F39/$G$39)*100 -> 108.14562 | N26: =(G39/$G$39)*100 -> 100
B27: Non-current Tax Assets (Net) | C27: 826.38 | D27: 989.16 | E27: 683.73 | F27: 672.89 | G27: 245.78 | I27: Loans & Advances | J27: =(C40/$G$40)*100 -> 129.95444 | K27: =(D40/$G$40)*100 -> 82.868841 | L27: =(E40/$G$40)*100 -> 85.399401 | M27: =(F40/$G$40)*100 -> 82.449989 | N27: =(G40/$G$40)*100 -> 100
B28: Other Current Tax Assets | C28: 4276.22 | D28: 3347.27 | E28: 2857.15 | F28: 3562.51 | G28: 3530.17 | I28: Other FA | J28: =(C42/$G$42)*100 -> 146.15074 | K28: =(D42/$G$42)*100 -> 172.58445 | L28: =(E42/$G$42)*100 -> 160.48071 | M28: =(F42/$G$42)*100 -> 105.64899 | N28: =(G42/$G$42)*100 -> 100
B29: Total Non-current Assets | C29: 269682.67 | D29: 232627.14 | E29: 207278.95 | F29: 192070.46 | G29: 191293.36 | I29: Other CAs | J29: =(C44/$G$44)*100 -> 147.15283 | K29: =(D44/$G$44)*100 -> 114.88644 | L29: =(E44/$G$44)*100 -> 99.558948 | M29: =(F44/$G$44)*100 -> 101.06267 | N29: =(G44/$G$44)*100 -> 100
B30: Current Assets | I30: Total CAs | J30: =(C45/$G$45)*100 -> 138.36872 | K30: =(D45/$G$45)*100 -> 116.34146 | L30: =(E45/$G$45)*100 -> 117.7771 | M30: =(F45/$G$45)*100 -> 105.08814 | N30: =(G45/$G$45)*100 -> 100
B31: Inventories | C31: 11159.15 | D31: 9536.42 | E31: 6196.96 | F31: 6805.57 | G31: 7059.13 | I31: Total Assets | J31: =(C47/$G$47)*100 -> 139.81819 | K31: =(D47/$G$47)*100 -> 119.99424 | L31: =(E47/$G$47)*100 -> 110.73183 | M31: =(F47/$G$47)*100 -> 101.3442 | N31: =(G47/$G$47)*100 -> 100
B32: Financial Assets
B33: Investments
B34: Investments of Insurance Business | C34: 900.69 | D34: 2339.22 | E34: 2088.62 | F34: 993.53 | G34: 931.12 | I34: Equity Share Capital | J34: =(C50/$G$50)*100 -> 100.12165 | K34: =(D50/$G$50)*100 -> 100.10644 | L34: =(E50/$G$50)*100 -> 100.06843 | M34: =(F50/$G$50)*100 -> 100.03041 | N34: =(G50/$G$50)*100 -> 100
B35: Other Investments | C35: 13905.64 | D35: 12382.87 | E35: 15482.11 | F35: 10500.75 | G35: 6012.98 | I35: Other Equity | J35: =(C51/$G$51)*100 -> 135.79725 | K35: =(D51/$G$51)*100 -> 130.53927 | L35: =(E51/$G$51)*100 -> 112.91192 | M35: =(F51/$G$51)*100 -> 97.638146 | N35: =(G51/$G$51)*100 -> 100
B36: Asset Held to Cover Linked Liabilities of Life Insurance Business | C36: 3662.84 | D36: 4022.72 | E36: 4717.99 | F36: 5189.98 | G36: 4931.49 | I36: Total Equity | J36: =(C54/$G$54)*100 -> 138.84987 | K36: =(D54/$G$54)*100 -> 131.23809 | L36: =(E54/$G$54)*100 -> 115.85988 | M36: =(F54/$G$54)*100 -> 102.78535 | N36: =(G54/$G$54)*100 -> 100
B37: Trade Receivables | C37: 5915.1 | D37: 5429.36 | E37: 4341.78 | F37: 5651.5 | G37: 6690.07
B38: Cash and Cash Equivalents | C38: 2312.56 | D38: 2240.7 | E38: 2617.04 | F38: 3072.8 | G38: 1223.69
B39: Bank Balances other than Cash and Cash Equivalents | C39: 1400.82 | D39: 1011.85 | E39: 2348.6 | F39: 740.3 | G39: 684.54
B40: Loans | C40: 22342.08 | D40: 14247.01 | E40: 14682.07 | F40: 14175 | G40: 17192.24 | I40: Financial Liabilities | J40: =(C58/$G$58)*100 -> 117.68751 | K40: =(D58/$G$58)*100 -> 82.11177 | L40: =(E58/$G$58)*100 -> 92.594569 | M40: =(F58/$G$58)*100 -> 103.63371 | N40: =(G58/$G$58)*100 -> 100
J41: - | K41: - | L41: - | M41: - | N41: -
B42: Other Financial Assets | C42: 2348.92 | D42: 2773.76 | E42: 2579.23 | F42: 1697.98 | G42: 1607.19 | J42: =(C60/$G$60)*100 -> 177.89476 | K42: =(D60/$G$60)*100 -> 153.18937 | L42: =(E60/$G$60)*100 -> 130.05555 | M42: =(F60/$G$60)*100 -> 103.30857 | N42: =(G60/$G$60)*100 -> 100
B43: Current Tax Assets (Net) | C43: 3.27 | D43: 0.11 | E43: 0.12 | F43: 0.38 | G43: 38.71 | J43: =(C61/$G$61)*100 -> 114.28858 | K43: =(D61/$G$61)*100 -> 122.93973 | L43: =(E61/$G$61)*100 -> 156.1077 | M43: =(F61/$G$61)*100 -> 96.103114 | N43: =(G61/$G$61)*100 -> 100
B44: Other Current Assets | C44: 3553.27 | D44: 2774.14 | E44: 2404.03 | F44: 2440.34 | G44: 2414.68 | I44: Provisions | J44: =(C62/$G$62)*100 -> 303.59167 | K44: =(D62/$G$62)*100 -> 290.56095 | L44: =(E62/$G$62)*100 -> 168.31715 | M44: =(F62/$G$62)*100 -> 124.87215 | N44: =(G62/$G$62)*100 -> 100
B45: Total Current Assets | C45: 67504.34 | D45: 56758.16 | E45: 57458.55 | F45: =SUM(F31:F44) -> 51268.13 | G45: =SUM(G31:G44) -> 48785.84 | I45: Deferred Tax Liabilities | J45: =(C63/$G$63)*100 -> 95.483321 | K45: =(D63/$G$63)*100 -> 96.425219 | L45: =(E63/$G$63)*100 -> 95.633387 | M45: =(F63/$G$63)*100 -> 79.127378 | N45: =(G63/$G$63)*100 -> 100
B46: Non-Current Assets/ Disposal Group Held for Sale | C46: 18.02 | D46: 9.53 | E46: 2318.81 | F46: 1077.21 | G46: 1094.73 | I46: Other NCLs | J46: =(C64/$G$64)*100 -> 18.660232 | K46: =(D64/$G$64)*100 -> 87.693899 | L46: =(E64/$G$64)*100 -> 151.89015 | M46: =(F64/$G$64)*100 -> 146.0301 | N46: =(G64/$G$64)*100 -> 100
B47: Total Assets | C47: 337205.03 | D47: 289394.83 | E47: 267056.31 | F47: 244415.8 | G47: 241173.93 | I47: Total NCLs | J47: =(C65/$G$65)*100 -> 139.34379 | K47: =(D65/$G$65)*100 -> 111.02095 | L47: =(E65/$G$65)*100 -> 108.27676 | M47: =(F65/$G$65)*100 -> 102.80668 | N47: =(G65/$G$65)*100 -> 100
B48: EQUITY AND LIABILITIES
B49: Equity
B50: Equity Share Capital | C50: 131.69 | D50: 131.67 | E50: 131.62 | F50: 131.57 | G50: 131.53
B51: Other Equity | C51: 78610.3 | D51: 75566.56 | E51: 65362.44 | F51: 56520.76 | G51: 57887.99
B52: Equity Attributable to Owners of the Company | C52: 78741.99 | D52: 75698.23 | E52: 65494.06 | F52: 56652.33 | G52: 58019.52 | I52: Trade Payables | J52: =(C73/$G$73)*100 -> 966.77668 | K52: =(D73/$G$73)*100 -> 671.83718 | L52: =(E73/$G$73)*100 -> 415.12651 | M52: =(F73/$G$73)*100 -> 228.68537 | N52: =(G73/$G$73)*100 -> 100
B53: Non-Controlling Interest | C53: 44170.83 | D53: 40476.48 | E53: 37067.54 | F53: 34335.42 | G53: 30502.58 | J53: =(C74/$G$74)*100 -> 214.99949 | K53: =(D74/$G$74)*100 -> 184.3647 | L53: =(E74/$G$74)*100 -> 131.82027 | M53: =(F74/$G$74)*100 -> 109.22885 | N53: =(G74/$G$74)*100 -> 100
B54: Total Equity | C54: 122912.82 | D54: 116174.71 | E54: 102561.6 | F54: 90987.75 | G54: 88522.1 | I54: Other FLs | J54: =(C75/$G$75)*100 -> 68.373945 | K54: =(D75/$G$75)*100 -> 56.633251 | L54: =(E75/$G$75)*100 -> 150.12702 | M54: =(F75/$G$75)*100 -> 124.28205 | N54: =(G75/$G$75)*100 -> 100
B55: Liabilities | I55: Other CLs | J55: =(C76/$G$76)*100 -> 134.70878 | K55: =(D76/$G$76)*100 -> 134.85252 | L55: =(E76/$G$76)*100 -> 116.90893 | M55: =(F76/$G$76)*100 -> 95.433441 | N55: =(G76/$G$76)*100 -> 100
B56: Non-current liabilities | I56: Provisions | J56: =(C77/$G$77)*100 -> 58.693021 | K56: =(D77/$G$77)*100 -> 66.270218 | L56: =(E77/$G$77)*100 -> 87.750725 | M56: =(F77/$G$77)*100 -> 106.57145 | N56: =(G77/$G$77)*100 -> 100
B57: Financial Liabilities | I57: Current Tax Liabilities | J57: =(C78/$G$78)*100 -> 239.63946 | K57: =(D78/$G$78)*100 -> 112.54037 | L57: =(E78/$G$78)*100 -> 137.49281 | M57: =(F78/$G$78)*100 -> 124.12409 | N57: =(G78/$G$78)*100 -> 100
B58: Borrowings | C58: 66712.46 | D58: 46545.96 | E58: 52488.25 | F58: 58745.91 | G58: 56686.1 | I58: Total CLs | J58: =(C79/$G$79)*100 -> 144.03087 | K58: =(D79/$G$79)*100 -> 119.90208 | L58: =(E79/$G$79)*100 -> 106.51972 | M58: =(F79/$G$79)*100 -> 95.56815 | N58: =(G79/$G$79)*100 -> 100
B59: Lease Liabilities | C59: 1410.73 | D59: 1319.38 | E59: 1447.48 | F59: 1366.14 | I59: Total Liabilities | J59: =(C81/$G$81)*100 -> 140.83085 | K59: =(D81/$G$81)*100 -> 113.83866 | L59: =(E81/$G$81)*100 -> 107.71931 | M59: =(F81/$G$81)*100 -> 100.51012 | N59: =(G81/$G$81)*100 -> 100
B60: Policyholder's Liabilities | C60: 67012.03 | D60: 57705.64 | E60: 48991.25 | F60: 38915.8 | G60: 37669.48 | I60: Total Equity and Liabilities | J60: =(C82/$G$82)*100 -> 139.81819 | K60: =(D82/$G$82)*100 -> 119.99424 | L60: =(E82/$G$82)*100 -> 110.73183 | M60: =(F82/$G$82)*100 -> 101.3442 | N60: =(G82/$G$82)*100 -> 100
B61: Other Financial Liabilities | C61: 398.57 | D61: 428.74 | E61: 544.41 | F61: 335.15 | G61: 348.74
B62: Provisions | C62: 765.81 | D62: 732.94 | E62: 424.58 | F62: 314.99 | G62: 252.25
B63: Deferred Tax Liabilities (Net) | C63: 8443.38 | D63: 8526.67 | E63: 8456.65 | F63: 6997.06 | G63: 8842.78
B64: Other Non-current Liabilities | C64: 16.24 | D64: 76.32 | E64: 132.19 | F64: 127.09 | G64: 87.03
B65: Total Non-current liabilities | C65: 144759.22 | D65: 115335.65 | E65: 112484.81 | F65: =SUM(F58:F64) -> 106802.14 | G65: =SUM(G58:G64) -> 103886.38
B66: Current Liabilities
B67: Financial Liabilities
B68: Borrowings | C68: 34635.46 | D68: 26457.29 | E68: 10037.04 | F68: 11988.13 | G68: 18378.52
B69: Lease Liabilities | C69: 279.91 | D69: 238.16 | E69: 221.13 | F69: 195.7
B70: Supplier's Credit | D70: 183.4
B71: Policyholder's Liabilities | C71: 2077.9 | D71: 3167.74 | E71: 3485.22 | F71: 2348.74 | G71: 2480.54
B72: Trade Payables
B73: - Total Outstanding dues of Micro and Small Enterprises | C73: 351.52 | D73: 244.28 | E73: 150.94 | F73: 83.15 | G73: 36.36
B74: - Total Outstanding dues of creditors other than Micro and Small Enterprises | C74: 13001.75 | D74: 11149.16 | E74: 7971.62 | F74: 6605.44 | G74: 6047.34
B75: Other Financial Liabilities | C75: 9859.01 | D75: 8166.09 | E75: 21647.19 | F75: 17920.54 | G75: 14419.25
B76: Other Current Liabilities | C76: 6438.15 | D76: 6445.02 | E76: 5587.44 | F76: 4561.06 | G76: 4779.31
B77: Provisions | C77: 722.47 | D77: 815.74 | E77: 1080.15 | F77: 1311.82 | G77: 1230.93
B78: Current Tax Liabilities (Net) | C78: 2166.82 | D78: 1017.59 | E78: 1243.21 | F78: 1122.33 | G78: 904.2
B79: Total Current liabilities | C79: 69532.99 | D79: 57884.47 | E79: 51423.94 | F79: =SUM(F68:F78) -> 46136.91 | G79: =SUM(G68:G78) -> 48276.45
B80: Liabilities directly associated with Non-Current Assets Held for Sale | E80: 585.96 | F80: 489 | G80: 489
B81: Total Liabilities | C81: =C65+C79 -> 214292.21 | D81: =D65+D79 -> 173220.12 | E81: =E65+E79 -> 163908.75 | F81: =F65+F79 -> 152939.05 | G81: =G65+G79 -> 152162.83
B82: Total Equity and Liabilities | C82: 337205.03 | D82: 289394.83 | E82: 267056.31 | F82: 244415.8 | G82: 241173.93
B87: No. of Equity Shares (in Crores) | C87: 65.84 | D87: 65.84 | E87: 65.84 | F87: 65.84 | G87: 65.84
B88: MPS (INR) | C88: 1632.7 | D88: 1664 | E88: 1450.55 | F88: 476.1 | G88: 830.15
B89: Value per Share (Book Value) | C89: =C54/C87 -> 1866.8411 | D89: =D54/D87 -> 1764.5005 | E89: =E54/E87 -> 1557.74 | F89: =F54/F87 -> 1381.9525 | G89: =G54/G87 -> 1344.5033
B90: Price to Book Value (P/BV) Ratio
B111: MPS (INR) as of Sept 1, 2023 (Rs)
B113: Price to Book Value (P/BV) Ratio as of Sep 1, 2023
B115: Tangible Value of the Firm (Total Equity - Intangible Assets)
B117: Tangible Value per Share (Tangible Value / No. of Equity Shares)
B120: Ex: Calculation of Liquidation Value:
B121: Realisable Value of the Assets
B122: Total Liabilities (Non CL + CL)
B123: Liquidation Value (Realisable value of the assets -Total Liabilities)
B124: Liquidation value per share (Liquidation value/ no. of equity shares)
B127: Liquidity Position (TCA/TCL)
B128: Total Current Assets/ Total Current Liabilities)

Sheet Horizontal Analysis of P&L
B2: Table 2.1: Statement of Profit and Loss of Grasim Industries Ltd. (India) | I2: Horizontal (Comparative) Analysis of Statement of Profit and Loss
B3: for the year ended (₹ in Crores) | I3: (Base Year March, 2019) Each item as a % of its March 2019 amount)
B4: Particulars | C4: March 31, 2023 | D4: March 31, 2022 | E4: March 31, 2021 | F4: March 31, 2020 | G4: March 31, 2019 | J4: March 31, 2023 | K4: March 31, 2022 | L4: March 31, 2021 | M4: March 31, 2020 | N4: March 31, 2019
B5: Revenue from operations | C5: 117627.08 | D5: 95701.13 | E5: 76397.81 | F5: 77625.1 | G5: 77200.25 | I5: Revenue from operations | J5: =(C5/$G$5)*100 -> 152.36619 | K5: =(D5/$G$5)*100 -> 123.96479 | L5: =(E5/$G$5)*100 -> 98.960573 | M5: =(F5/$G$5)*100 -> 100.55032 | N5: =(G5/$G$5)*100 -> 100
B6: Other Income | C6: 3612.05 | D6: 821.34 | E6: 1051.96 | F6: 966.61 | G6: 827.69 | I6: Other Income | J6: =(C6/$G$6)*100 -> 436.40131 | K6: =(D6/$G$6)*100 -> 99.232805 | L6: =(E6/$G$6)*100 -> 127.09589 | M6: =(F6/$G$6)*100 -> 116.78406 | N6: =(G6/$G$6)*100 -> 100
B7: Total Income (I) | C7: 121239.13 | D7: 96522.47 | E7: 77449.77 | F7: 78591.71 | G7: 78027.94 | I7: Total Income (I) | J7: =(C7/$G$7)*100 -> 155.37912 | K7: =(D7/$G$7)*100 -> 123.70245 | L7: =(E7/$G$7)*100 -> 99.259022 | M7: =(F7/$G$7)*100 -> 100.72252 | N7: =(G7/$G$7)*100 -> 100
B8: Expenses | I8: Expenses
B9: Cost of materials consumed | C9: 21622.26 | D9: 16889.6 | E9: 11006.75 | F9: 14618.05 | G9: 15261.12 | I9: Cost of materials consumed | J9: =(C9/$G$9)*100 -> 141.682 | K9: =(D9/$G$9)*100 -> 110.67078 | L9: =(E9/$G$9)*100 -> 72.122819 | M9: =(F9/$G$9)*100 -> 95.78622 | N9: =(G9/$G$9)*100 -> 100
B10: Purchases of stock-in-trade | C10: 1824.35 | D10: 1404.56 | E10: 898.44 | F10: 1469.86 | G10: 1507.01 | I10: Purchases of stock-in-trade | J10: =(C10/$G$10)*100 -> 121.05759 | K10: =(D10/$G$10)*100 -> 93.20177 | L10: =(E10/$G$10)*100 -> 59.617388 | M10: =(F10/$G$10)*100 -> 97.534854 | N10: =(G10/$G$10)*100 -> 100
B11: Changes in inventories of finished goods, work-in-progress and stock-in-trade | C11: 834.66 | D11: 921.74 | E11: 724.03 | F11: 525.9 | G11: 79.89 | I11: Changes in inventories of finished goods, work-in-progress and stock-in-trade | J11: =(C11/$G$11)*100 -> 1044.7615 | K11: =(D11/$G$11)*100 -> 1153.7614 | L11: =(E11/$G$11)*100 -> 906.28364 | M11: =(F11/$G$11)*100 -> 658.28014 | N11: =(G11/$G$11)*100 -> 100
B12: Employee benefits expense | C12: 7193.86 | D12: 6327.71 | E12: 5534.74 | F12: 5864.53 | G12: 5428.21 | I12: Employee benefits expense | J12: =(C12/$G$12)*100 -> 132.5273 | K12: =(D12/$G$12)*100 -> 116.57084 | L12: =(E12/$G$12)*100 -> 101.96253 | M12: =(F12/$G$12)*100 -> 108.03801 | N12: =(G12/$G$12)*100 -> 100
I13: Finance Cost relating to NBFC/HFC's Business | J13: =(C18/$G$18)*100 -> 116.62346 | K13: =(D18/$G$18)*100 -> 85.929514 | L13: =(E18/$G$18)*100 -> 96.652494 | M13: =(F18/$G$18)*100 -> 113.27447 | N13: =(G18/$G$18)*100 -> 100
B14: Power and Fuel | C14: 23168.73 | D14: 15520.7 | E14: 10363.78 | F14: 11436.68 | G14: 12423.45 | I14: Other Finance Costs | J14: =(C19/$G$19)*100 -> 65.689977 | K14: =(D19/$G$19)*100 -> 64.467498 | L14: =(E19/$G$19)*100 -> 90.000746 | M14: =(F19/$G$19)*100 -> 116.35197 | N14: =(G19/$G$19)*100 -> 100
B15: Freight and Handling Expenses | C15: 15024.93 | D15: 12584.1 | E15: 10381.83 | F15: 10058.06 | G15: 10619.15 | I15: Depreciation and Amortisation expense | J15: =(C20/$G$20)*100 -> 127.44625 | K15: =(D20/$G$20)*100 -> 116.51154 | L15: =(E20/$G$20)*100 -> 112.93674 | M15: =(F20/$G$20)*100 -> 113.1445 | N15: =(G20/$G$20)*100 -> 100
B16: Change in Valuation of Liability in respect of Insurance Policies | C16: 7451.57 | D16: 4240.83 | E16: 4374.84 | F16: 1032.26 | G16: 1408.88 | I16: Other Expenses | J16: =(C21/$G$21)*100 -> 159.43537 | K16: =(D21/$G$21)*100 -> 132.04116 | L16: =(E21/$G$21)*100 -> 106.18982 | M16: =(F21/$G$21)*100 -> 116.50091 | N16: =(G21/$G$21)*100 -> 100
B17: Benefits Paid - Insurance Business | C17: 5467.75 | D17: 6702.55 | E17: 4445.05 | F17: 5177.01 | G17: 4553.57 | I17: Total Expenses (II) | J17: =(C22/$G$22)*100 -> 151.88824 | K17: =(D22/$G$22)*100 -> 119.94397 | L17: =(E22/$G$22)*100 -> 96.183599 | M17: =(F22/$G$22)*100 -> 101.31025 | N17: =(G22/$G$22)*100 -> 100
B18: Finance Cost relating to NBFC/HFC's Business | C18: 4723.46 | D18: 3480.3 | E18: 3914.6 | F18: 4587.82 | G18: 4050.18 | I18: Profit/(Loss) before Exceptional Items & Tax
B19: Other Finance Costs | C19: 1320.27 | D19: 1295.7 | E19: 1808.88 | F19: 2338.5 | G19: 2009.85 | I19: Exceptional Items
B20: Depreciation and Amortisation expense | C20: 4551.59 | D20: 4161.07 | E20: 4033.4 | F20: 4040.82 | G20: 3571.38 | I20: Profit Before Tax | J20: =(C28/$G$28)*100 -> 50676.91 | K20: =(D28/$G$28)*100 -> 43450.998 | L20: =(E28/$G$28)*100 -> 33625.017 | M20: =(F28/$G$28)*100 -> 1934.6869 | N20: =(G28/$G$28)*100 -> 100
B21: Other Expenses | C21: 15119.24 | D21: 12521.45 | E21: 10069.97 | F21: 11047.77 | G21: 9482.99 | I21: Tax expense
B22: Total Expenses (II) | C22: 106633.35 | D22: 84206.83 | E22: 67525.83 | F22: 71125 | G22: 70205.14 | I22: Current Tax | J22: =(C31/$G$31)*100 -> 146.73292 | K22: =(D31/$G$31)*100 -> 83.542789 | L22: =(E31/$G$31)*100 -> 83.756519 | M22: =(F31/$G$31)*100 -> 68.709071 | N22: =(G31/$G$31)*100 -> 100
B23: Profit from Continuing Operations Before Share in Profit of (I - II) | C23: 14605.78 | D23: 12315.64 | E23: 9923.94 | F23: 7466.71 | G23: 7822.8 | I23: Deferred Tax | J23: =(C32/$G$32)*100 -> 227.6073 | K23: =(D32/$G$32)*100 -> 19.076242 | L23: =(E32/$G$32)*100 -> 1120.7318 | M23: =(F32/$G$32)*100 -> 1722.6511 | N23: =(G32/$G$32)*100 -> 100
B24: Equity Accounted Investees, Exceptional Items and Tax | I24: Total Tax Expenses | J24: =(C33/$G$33)*100 -> 150.84466 | K24: =(D33/$G$33)*100 -> 80.055153 | L24: =(E33/$G$33)*100 -> 124.94997 | M24: =(F33/$G$33)*100 -> 1.2671992 | N24: =(G33/$G$33)*100 -> 100
B25: Share in Profit of Equity Accounted Investees | C25: 208.96 | D25: 380.33 | E25: 189.22 | I25: Profit for the year (PAT) | J25: =(C34/$G$34)*100 -> 403.61564 | K25: =(D34/$G$34)*100 -> 389.49227 | L25: =(E34/$G$34)*100 -> 245.89724 | M25: =(F34/$G$34)*100 -> 243.28279 | N25: =(G34/$G$34)*100 -> 100
B26: Profit from Continuing Operations Before Tax and Exceptional Items | C26: 14814.74 | D26: 12695.97 | E26: 10113.16 | I26: Other Comprehensive Income (net of Tax)
B27: Exceptional Items | C27: 88.03 | D27: 69.11 | E27: 341.73 | I27: Items that will not be reclassified to Profit and Loss | J27: =(C43/$G$43)*100 -> 128.06633 | K27: =(D43/$G$43)*100 -> 127.98751 | L27: =(E43/$G$43)*100 -> 259.78174 | M27: =(F43/$G$43)*100 -> 204.95603 | N27: =(G43/$G$43)*100 -> 100
B28: Profit from Continuing Operations Before Tax (PBT) | C28: 14726.71 | D28: 12626.86 | E28: 9771.43 | F28: 562.22 | G28: 29.06
B29: Tax expense
B30: Tax Expense of Continuing Operations (Net)
B31: Current Tax | C31: 3432.67 | D31: 1954.4 | E31: 1959.4 | F31: 1607.38 | G31: 2339.4
B32: Deferred Tax | C32: 215.84 | D32: 18.09 | E32: 1062.79 | F32: 1633.59 | G32: 94.83 | I32: Earnings Per Equity Share attributable to the Owners of the Company | J32: =(C66/$G$66)*100 -> 403.64907 | K32: =(D66/$G$66)*100 -> 419.87578 | L32: =(E66/$G$66)*100 -> 244.09938 | M32: =(F66/$G$66)*100 -> 261.7236 | N32: =(G66/$G$66)*100 -> 100
B33: Total Tax Expenses | C33: 3648.51 | D33: 1936.31 | E33: 3022.19 | F33: 30.65 | G33: 2418.72 | I33: Basic and Diluted EPS (of Re 1/- each) (INR)
B34: Profit for the Year from Continuing Operations (III) (PAT) | C34: 11078.2 | D34: 10690.55 | E34: 6749.24 | F34: 6677.48 | G34: 2744.74 | I34: Significant Accounting Policies
B35: Discontinued Operations | I35: The accompanying notes are an integral part of these financial statements.
B36: Profit Before Tax from Discontinued Operations | D36: 352.52 | E36: 162.79 | F36: 90.03 | G36: 54.94
B37: Exceptional Items | D37: 670.71 | E37: 166.5 | F37: 36.63 | G37: 15.31
B38: Tax Expenses of Discontinued Operations | D38: 440.07 | E38: 66.1
B39: Less: Reversal / (Provision) of Impairment of Assets Classified as Held for Sale | D39: 67.42 | E39: 25.73 | F39: 53.4 | G39: 39.63
B40: Profit for the Year from Discontinued Operations (IV) | D40: 515.74 | E40: 237.46
B41: Profit for the Year (V = III + IV) | C41: 11078.2 | D41: 11206.29 | E41: 6986.7 | F41: 6677.48 | G41: 2744.74
B42: Other Comprehensive Income (net of Tax)
B43: A (i) Items that will not be reclassified to Profit or Loss | C43: 3444.28 | D43: 3442.16 | E43: 6986.7 | F43: 5512.19 | G43: 2689.45
B44: (ii) Income Tax relating to items that will not be reclassified to Profit or Loss | C44: 387.85 | D44: 221.77 | E44: 387.07 | F44: 373.62 | G44: 31.06
B45: B (i) Items that will be reclassified to Profit or Loss | C45: 182.04 | D45: 63.88 | E45: 163.53 | F45: 145.53 | G45: 77.38
B46: (ii) Income Tax relating to items that will be reclassified to Profit or Loss | C46: 57.69 | D46: 3.47 | E46: 18.75 | F46: 8.96 | G46: 16.63
B47: Other Comprehensive Income for the Year (VI) | C47: 3180.78 | D47: 3280.8 | E47: 4840.92 | F47: 5002 | G47: 2781.26
B48: Total comprehensive income for the Year (V+VI) | C48: 7897.42 | D48: 14487.09 | E48: 11827.62 | F48: 1675.48 | G48: 36.52
B49: Profit from Continuing Operations Attributable to:
B50: Owners of the Company | C50: 6827.26 | D50: 7102.37 | E50: 4128.41 | F50: 4425.19 | G50: 1692.99
B51: Non-Controlling Interest | C51: 4250.94 | D51: 3588.18 | E51: 2620.83 | F51: 2252.29 | G51: 1051.75
C52: 11078.2 | D52: 10690.55 | E52: 6749.24 | F52: 6677.48 | G52: 2744.74
B53: Profit Attributable to:
B54: Owners of the Company | C54: 6827.26 | D54: 7549.78 | E54: 4304.82 | F54: 4425.19 | G54: 1692.99
B55: Non-Controlling Interest | C55: 4250.94 | D55: 3656.51 | E55: 2681.88 | F55: 2252.29 | G55: 1051.75
C56: 11078.2 | D56: 11206.29 | E56: 6986.7 | F56: 6677.48 | G56: 2744.74
B57: Other Comprehensive Income Attributable to:
B58: Owners of the Company | C58: 3104.23 | D58: 3281.85 | E58: 4780.54 | F58: 5067.74 | G58: 2822.5
B59: Non-Controlling Interest | C59: 76.55 | D59: 1.05 | E59: 60.38 | F59: 65.74 | G59: 41.24
C60: 3180.78 | D60: 3280.8 | E60: 4840.92 | F60: 5002 | G60: 2781.26
B61: Total Comprehensive Income Attributable to:
B62: Owners of the Company | C62: 3723.03 | D62: 10831.63 | E62: 9085.36 | F62: 642.55 | G62: 1129.51
B63: Non-Controlling Interest | C63: 4174.39 | D63: 3655.46 | E63: 2742.26 | F63: 2318.03 | G63: 1092.99
C64: 7897.42 | D64: 14487.09 | E64: 11827.62 | F64: 1675.48 | G64: 36.52
B65: Earnings Per Equity Share (Face Value D 2 each) - Continuing Operations
B66: Basic (₹) | C66: 103.98 | D66: 108.16 | E66: 62.88 | F66: 67.42 | G66: 25.76
B67: Diluted (₹) | C67: 103.88 | D67: 108 | E67: 62.82 | F67: 67.38 | G67: 25.74
B68: Earnings Per Equity Share (Face Value D 2 each) - Discontinued Operations
B69: Basic (₹) | D69: 6.82 | E69: 2.69
B70: Diluted (₹) | D70: 6.8 | E70: 2.68
B71: Earnings Per Equity Share (Face Value D 2 each) - Continuing and Discontinued Operations
B72: Basic (₹) | C72: 103.98 | D72: 114.98 | E72: 65.57 | F72: 67.42 | G72: 25.76
B73: Diluted (₹) | C73: 103.88 | D73: 114.8 | E73: 65.5 | F73: 67.38 | G73: 25.74

Sheet Ratio Analysis
B2: Table 1.1: Balance Sheet of GRASIM INDUSTRIES LTD (India) | I2: Financial Statement Analysis: Ratio Analysis
B3: (₹ in Crores) | R3: DuPont Analysis - Drivers of Profitability (ROE)
B4: Particulars | C4: As at March 31, 2023 | D4: As at March 31, 2022 | E4: As at March 31, 2021 | F4: As at March 31, 2020 | G4: As at March 31, 2019 | I4: Particulars | J4: Unit of Measure | K4: March 31, 2023 | L4: March 31, 2022 | M4: March 31, 2021 | N4: March 31, 2020 | O4: March 31, 2019 | R4: Sl. No. | S4: Particulars | T4: Unit of Measure | U4: March 31, 2023 | V4: March 31, 2022 | W4: March 31, 2021 | X4: March 31, 2020 | Y4: March 31, 2019
B5: ASSETS | I5: (A) Profitability Ratios | R5: 1 | S5: ROE | T5: % | U5: =K8 -> 0.092670663 | V5: =L8 -> 0.097748289 | W5: =M8 -> 0.0697418 | X5: =N8 -> 0.074396809 | Y5: =O8 -> 0.062012537
B6: Non-Current Assets | I6: Net Income Margin (PAT/Revenue from Operations) | J6: % | K6: =C92/C120 -> 10.617887 | L6: =D92/D120 -> 8.951937 | M6: =E92/E120 -> 11.319469 | N6: =F92/F120 -> 11.624909 | O6: =G92/G120 -> 28.126617 | S6: Drivers of ROE
B7: Property, Plant and Equipment | C7: 63753.53 | D7: 58148.57 | E7: 53767.33 | F7: 55758.44 | G7: 55652.22 | I7: Return on Assets (ROA) or ROI (PAT/Avg. TA) | J7: % | K7: =C120/J89 -> 0.035359727 | L7: =D120/K89 -> 0.038424038 | M7: =E120/L89 -> 0.026391429 | N7: =F120/M89 -> 0.027502559 | O7: =G120/N89 -> 0.022761498 | R7: 2 | S7: ROA | T7: % | U7: =K7 -> 0.035359727 | V7: =L7 -> 0.038424038 | W7: =M7 -> 0.026391429 | X7: =N7 -> 0.027502559 | Y7: =O7 -> 0.022761498
B8: Capital Work-in-progress | C8: 7730.18 | D8: 6572.18 | E8: 5719.43 | F8: 3822.45 | G8: 2728.2 | I8: Return on Networth/Equity (ROE) (PAT/ Avg. Equity) | J8: % | K8: =C120/J90 -> 0.092670663 | L8: =D120/K90 -> 0.097748289 | M8: =E120/L90 -> 0.0697418 | N8: =F120/M90 -> 0.074396809 | O8: =G120/N90 -> 0.062012537 | R8: 3 | S8: Leverage | T8: Times | U8: =K32 -> 2.7434488 | V8: =L32 -> 2.4910312 | W8: =M32 -> 2.6038626 | X8: =N32 -> 2.6862495 | Y8: =O32 -> 2.7244488
B9: Investment Property | C9: 14.37 | D9: 14.81 | E9: 15.24 | F9: 15.67 | G9: 16.11 | I9: EBIT Margin (EBIT/Revenue from Operations) | J9: % | K9: =J91/C92 -> 0.14484301 | L9: =K91/D92 -> 0.17001158 | M9: =L91/E92 -> 0.19104553 | N9: =M91/F92 -> 0.17296493 | O9: =N91/G92 -> 0.16910748 | S9: Drivers of ROA
B10: Goodwill | C10: 20137.55 | D10: 20058.5 | E10: 20013.86 | F10: 20046.5 | G10: 21346.39 | I10: EBITDA Margin (EBITDA/Revenue from Operations) | J10: % | K10: =J93/C92 -> 0.18353809 | L10: =K93/D92 -> 0.21349142 | M10: =L93/E92 -> 0.24384024 | N10: =M93/F92 -> 0.22502052 | O10: =N93/G92 -> 0.21536873 | R10: 4 | S10: Efficiency of Total Assets | T10: Times | U10: =K14 -> 0.3754456 | V10: =L14 -> 0.34396957 | W10: =M14 -> 0.29873695 | X10: =N14 -> 0.31971475 | Y10: =O14 -> 0.64020394
B11: Other Intangible Assets | C11: 8591.89 | D11: 8895.41 | E11: 9254.48 | F11: 9684.29 | G11: 10114.47 | I11: Return on Capital Employed (ROCE) (EBIT/Avg. CE) | J11: % | K11: =J91/J95 -> 0.068261461 | L11: =K91/K95 -> 0.072774525 | M11: =L91/L95 -> 0.070524585 | N11: =M91/M95 -> 0.068646376 | O11: =N91/N95 -> 0.13535833 | R11: 5 | S11: Net Income Margin | T11: % | U11: =K6 -> 10.617887 | V11: =L6 -> 8.951937 | W11: =M6 -> 11.319469 | X11: =N6 -> 11.624909 | Y11: =O6 -> 28.126617
B12: Intangible Assets under Development | C12: 47.5 | D12: 42.94 | E12: 49.26 | F12: 81.68 | G12: 37.77 | S12: Drivers of Net Income
B13: Right of Use Assets | C13: 2399.03 | D13: 1878.83 | E13: 1971.89 | F13: 2062.63 | I13: (B) Efficiency Analysis | R13: 6 | S13: Material Expense (% Revenue from Operations) | T13: % | U13: {='Vertical Analysis of P&L'!J9:J11} -> 18.382043 | V13: {='Vertical Analysis of P&L'!K9:K11} -> 17.648276 | W13: {='Vertical Analysis of P&L'!L9:L11} -> 14.407154 | X13: {='Vertical Analysis of P&L'!M9:M11} -> 18.831602 | Y13: {='Vertical Analysis of P&L'!N9:N11} -> 19.768226
B14: Investment in Equity Accounted Investees | C14: 11016.84 | D14: 7050.17 | E14: 6837.66 | F14: 6533.09 | G14: 6284.29 | I14: Efficiency of Total Assets (Net Sales/Avg. TA) | J14: Times | K14: =C92/J89 -> 0.3754456 | L14: =D92/K89 -> 0.34396957 | M14: =E92/L89 -> 0.29873695 | N14: =F92/M89 -> 0.31971475 | O14: =G92/N89 -> 0.64020394 | R14: 7 | S14: Labour Expense (% Revenue from Operations) | T14: % | U14: 1.5509609 | V14: 1.4676525 | W14: 1.1760023 | X14: 1.893537 | Y14: 1.9520792
B15: Financial Assets | I15: Efficiency of Non-current Assets/Net Fixed Assets (Net Sales/Avg.NFA) | J15: Times | R15: 8 | S15: Depreciation and Amortization (% Revenue from Operations) | T15: % | U15: 0.7095815 | V15: 0.96314432 | W15: 0.94771041 | X15: 0.67748705 | Y15: 0.10348412
B16: Investments | I16: Efficiency of Current Assets (Net Sales/Avg. CA) | J16: Times | K16: =C92/J97 -> 1.8932032 | L16: =D92/K97 -> 1.6757816 | M16: =E92/L97 -> 2.6592321 | N16: =F92/M97 -> #DIV/0! | O16: =G92/N97 -> #DIV/0! | R16: 9 | S16: Other Expenses (% Revenue from Operations) | T16: % | U16: ='Vertical Analysis of P&L'!J20 -> 12.853537 | V16: ='Vertical Analysis of P&L'!K20 -> 13.08391 | W16: ='Vertical Analysis of P&L'!L20 -> 10.52231 | X16: ='Vertical Analysis of P&L'!M20 -> 11.544033 | Y16: ='Vertical Analysis of P&L'!N20 -> 12.283626
B17: Investments of Insurance Business | C17: 39523.43 | D17: 30952.64 | E17: 25046.58 | F17: 19269.34 | G17: 15601.37 | I17: Inventory Efficiency Ratio (Net Sales/Avg. Inventory) | J17: Times | K17: =C92/J98 -> 11.367368 | L17: =D92/K98 -> 12.165362 | M17: =E92/L98 -> 11.751222 | N17: =F92/M98 -> 11.197516 | O17: =G92/N98 -> 21.872455 | R17: 10 | S17: Finance Expense (% Revenue from Operations) | T17: % | U17: {='Vertical Analysis of P&L'!J17:J18} -> 4.0156229 | V17: {='Vertical Analysis of P&L'!K17:K18} -> 3.6366342 | W17: {='Vertical Analysis of P&L'!L17:L18} -> 5.1239689 | X17: {='Vertical Analysis of P&L'!M17:M18} -> 5.9102275 | Y17: {='Vertical Analysis of P&L'!N17:N18} -> 5.2463302
B18: Other Investments | C18: 9502.9 | D18: 13881.17 | E18: 10592.62 | F18: 6211.67 | G18: 8751.22 | I18: Inventory-Holding Days (365/ITR) | J18: Days | K18: =365/K17 -> 32.109456 | L18: =365/L17 -> 30.003218 | M18: =365/M17 -> 31.060599 | N18: =365/N17 -> 32.596515 | O18: =365/O17 -> 16.687656 | R18: 11 | S18: Tax Expense (% Revenue from Operations) | T18: % | U18: 1.1224201 | V18: 1.3539025 | W18: 2.3677118 | X18: 3.0125565 | Y18: 2.6034242
B19: Asset Held to Cover Linked Liabilities of Life Insurance Business | C19: 26842.95 | D19: 26137.33 | E19: 23251.2 | F19: 17638.81 | G19: 20234.85 | I19: Accounts Recevables (A/R) Efficiency (Net Sales/Avg. TR) | J19: Times | S19: Drivers of Efficiency of Total Assets
B20: Trade Receivables | C20: 6.82 | I20: Accounts Recevables (A/R) Collection Days (365/DTR) | J20: Days | R20: 12 | S20: Efficiency of Current Assets | T20: Times | U20: =K16 -> 1.8932032 | V20: =L16 -> 1.6757816 | W20: =M16 -> 2.6592321 | X20: =N16 -> #DIV/0! | Y20: =O16 -> #DIV/0!
B21: Loans | C21: 70871.12 | D21: 51954.12 | E21: 45743.75 | F21: 46054.89 | G21: 46384.67 | I21: Accounts Payables (A/P) Efficiency Ratio | J21: Times | K21: =C92/J100 -> 6.1746531 | L21: =D92/K100 -> 6.1923561 | M21: =E92/L100 -> 6.6624903 | N21: =F92/M100 -> 7.9775529 | O21: =G92/N100 -> 12.689687 | R21: 13 | S21: Efficiency of Non-current Assets | T21: Times
B22: Other Financial Assets | C22: 3759.7 | D22: 2458 | E22: 1269.33 | F22: 518.03 | G22: 318.9 | I22: Payables Payment Days (365/APTR) | J22: Days | K22: =365/K21 -> 59.112632 | L22: =365/L21 -> 58.943638 | M22: =365/M21 -> 54.78432 | N22: =365/N21 -> 45.753379 | O22: =365/O21 -> 28.763514 | S22: Drivers of Efficiency of Non-current Assets
B23: Deferred Tax Assets (Net) | C23: 382.26 | D23: 246.04 | E23: 205.44 | F23: 137.57 | G23: 46.95 | I23: Cash Conversion Cycle (CCC) | J23: Days | R23: 14 | S23: PPE (Net Sales/PPE) | T23: Times | U23: =C92/C7 -> 1.8450285 | V23: =D92/D7 -> 1.6458037 | W23: =E92/E7 -> 1.4208965 | X23: =F92/F7 -> 1.3921677 | Y23: =G92/G7 -> 1.3871908
B24: Non-current Tax Assets (Net) | C24: 826.38 | D24: 989.16 | E24: 683.73 | F24: 672.89 | G24: 245.78 | I24: (CCC = Inventory Holding days + Receivables Collection Days - Payables Payment Days) | R24: 15 | S24: Intangible Assets (Net Sales/Intangible Assets) | T24: Times | U24: =C92/C11 -> 13.690478 | V24: =D92/D11 -> 10.758484 | W24: =E92/E11 -> 8.2552245 | X24: =F92/F11 -> 8.0155695 | Y24: =G92/G11 -> 7.632654
B25: Other Current Tax Assets | C25: 4276.22 | D25: 3347.27 | E25: 2857.15 | F25: 3562.51 | G25: 3530.17 | I25: Operating Cycle | S25: Drivers of Efficiency of Current Assets
B26: Total Non-current Assets | C26: 269682.67 | D26: 232627.14 | E26: 207278.95 | F26: 192070.46 | G26: 191293.36 | I26: (C) Liquidity Analysis | R26: 16 | S26: Inventory | T26: Times | U26: =K17 -> 11.367368 | V26: =L17 -> 12.165362 | W26: =M17 -> 11.751222 | X26: =N17 -> 11.197516 | Y26: =O17 -> 21.872455
B27: Current Assets | I27: Current Ratio (CA/CL) | J27: Times | K27: =C41/C61 -> 0.46632152 | L27: =D41/D61 -> 0.49211289 | M27: =E41/E61 -> 0.51081164 | N27: =F41/F61 -> 0 | O27: =G41/G61 -> 0 | R27: 17 | S27: Accounts Recevables (A/R) | T27: Times
B28: Inventories | C28: 11159.15 | D28: 9536.42 | E28: 6196.96 | F28: 6805.57 | G28: 7059.13 | I28: Quick Ratio (QA/CL) | J28: Times | K28: =(C28-C41)/C75 -> -0.81033751 | L28: =(D28-D41)/D75 -> -0.81579291 | M28: =(E28-E41)/E75 -> -0.99684291 | N28: =(F28-F41)/F75 -> 0.14750814 | O28: =(G28-G41)/G75 -> 0.14622305 | R28: 18 | S28: Inventory-Holding Days | T28: Days | U28: =K18 -> 32.109456 | V28: =L18 -> 30.003218 | W28: =M18 -> 31.060599 | X28: =N18 -> 32.596515 | Y28: =O18 -> 16.687656
B29: Financial Assets | R29: 19 | S29: Accounts Recevables (A/R) Collection Days | T29: Days
B30: Investments
B31: Investments of Insurance Business | C31: 900.69 | D31: 2339.22 | E31: 2088.62 | F31: 993.53 | G31: 931.12 | I31: (D) Solvency Analysis
B32: Other Investments | C32: 13905.64 | D32: 12382.87 | E32: 15482.11 | F32: 10500.75 | G32: 6012.98 | I32: Leverage (TA/SHF) Ratio | J32: Times | K32: =C43/C50 -> 2.7434488 | L32: =D43/D50 -> 2.4910312 | M32: =E43/E50 -> 2.6038626 | N32: =F43/F50 -> 2.6862495 | O32: =G43/G50 -> 2.7244488
B33: Asset Held to Cover Linked Liabilities of Life Insurance Business | C33: 3662.84 | D33: 4022.72 | E33: 4717.99 | F33: 5189.98 | G33: 4931.49 | I33: Debt to Equity Ratio (Total Liabilities/Equity) | J33: Times | K33: =C77/C50 -> 1.7434488 | L33: =D77/D50 -> 1.4910312 | M33: =E77/E50 -> 1.5981493 | N33: =F77/F50 -> 1.6808752 | O33: =G77/G50 -> 1.7189248
B34: Trade Receivables | C34: 5915.1 | D34: 5429.36 | E34: 4341.78 | F34: 5651.5 | G34: 6690.07 | I34: Debt to Equity Ratio (LT Debt/Equity) | J34: Times | K34: =(C61/C50) -> 1.177739 | L34: =(D61/D50) -> 0.9927776 | M34: =(E61/E50) -> 1.0967537 | N34: =(F61/F50) -> 1.1738079 | O34: =(G61/G50) -> 1.1735643
B35: Cash and Cash Equivalents | C35: 2312.56 | D35: 2240.7 | E35: 2617.04 | F35: 3072.8 | G35: 1223.69 | I35: Interest Coverage Ratio (EBIT/Finance Cost) | J35: Times | K35: =J91/(C104+C105) -> 2.8190306 | L35: =K91/(D104+D105) -> 3.4066792 | M35: =L91/(E104+E105) -> 2.5501024 | N35: =M91/(F104+F105) -> 1.9384637 | O35: =N91/(G104+G105) -> 2.1543029
B36: Bank Balances other than Cash and Cash Equivalents | C36: 1400.82 | D36: 1011.85 | E36: 2348.6 | F36: 740.3 | G36: 684.54 | I36: Leverage (Avg. TA/Avg. SHF) Ratio | J36: Times | K36: =J89/J90 -> 2.6207969 | L36: =K89/K90 -> 2.5439358 | M36: =L89/L90 -> 2.6425928 | N36: =M89/M90 -> 2.7050868 | O36: =N89/N90 -> 2.7244488
B37: Loans | C37: 22342.08 | D37: 14247.01 | E37: 14682.07 | F37: 14175 | G37: 17192.24
B38: Other Financial Assets | C38: 2348.92 | D38: 2773.76 | E38: 2579.23 | F38: 1697.98 | G38: 1607.19 | I38: (E) Valuation Ratios
B39: Current Tax Assets (Net) | C39: 3.27 | D39: 0.11 | E39: 0.12 | F39: 0.38 | G39: 38.71 | I39: Price Earning (P/E) Ratio | J39: Times
B40: Other Current Assets | C40: 3553.27 | D40: 2774.14 | E40: 2404.03 | F40: 2440.34 | G40: 2414.68 | I40: Price to Book Value ( P/BV) Ratio | J40: Times | K40: ='Balance Sheet'!C84/('Ratio Analysis'!C92/J105) -> 0.91387942 | L40: ='Balance Sheet'!D84/('Ratio Analysis'!D92/K105) -> 1.1447907 | M40: ='Balance Sheet'!E84/('Ratio Analysis'!E92/L105) -> 1.250091 | N40: ='Balance Sheet'!F84/('Ratio Analysis'!F92/M105) -> 0.40381815 | O40: ='Balance Sheet'!G84/('Ratio Analysis'!G92/N105) -> 0.70799092
B41: Total Current Assets | C41: 67504.34 | D41: 56758.16 | E41: 57458.55 | I41: Price to Sales (P/S) Ratio | J41: Times | K41: ='Balance Sheet'!C84/('Ratio Analysis'!J105/'Ratio Analysis'!C92) -> 2916915.8 | L41: ='Balance Sheet'!D84/('Ratio Analysis'!K105/'Ratio Analysis'!D92) -> 2418692 | M41: ='Balance Sheet'!E84/('Ratio Analysis'!L105/'Ratio Analysis'!E92) -> 1683153.8 | N41: ='Balance Sheet'!F84/('Ratio Analysis'!M105/'Ratio Analysis'!F92) -> 561320.02 | O41: ='Balance Sheet'!G84/('Ratio Analysis'!N105/'Ratio Analysis'!G92) -> 973386.81
B42: Non-Current Assets/ Disposal Group Held for Sale | C42: 18.02 | D42: 9.53 | E42: 2318.81 | F42: 1077.21 | G42: 1094.73 | I42: Dividend Yield (DPS/MPS) Ratio | J42: %
B43: Total Assets | C43: 337205.03 | D43: 289394.83 | E43: 267056.31 | F43: 244415.8 | G43: 241173.93
B44: EQUITY AND LIABILITIES
B45: Equity
B46: Equity Share Capital | C46: 131.69 | D46: 131.67 | E46: 131.62 | F46: 131.57 | G46: 131.53
B47: Other Equity | C47: 78610.3 | D47: 75566.56 | E47: 65362.44 | F47: 56520.76 | G47: 57887.99
B48: Equity Attributable to Owners of the Company | C48: 78741.99 | D48: 75698.23 | E48: 65494.06 | F48: 56652.33 | G48: 58019.52
B49: Non-Controlling Interest | C49: 44170.83 | D49: 40476.48 | E49: 37067.54 | F49: 34335.42 | G49: 30502.58
B50: Total Equity | C50: 122912.82 | D50: 116174.71 | E50: 102561.6 | F50: 90987.75 | G50: 88522.1
B51: Liabilities
B52: Non-current liabilities
B53: Financial Liabilities
B54: Borrowings | C54: 66712.46 | D54: 46545.96 | E54: 52488.25 | F54: 58745.91 | G54: 56686.1
B55: Lease Liabilities | C55: 1410.73 | D55: 1319.38 | E55: 1447.48 | F55: 1366.14
B56: Policyholder's Liabilities | C56: 67012.03 | D56: 57705.64 | E56: 48991.25 | F56: 38915.8 | G56: 37669.48
B57: Other Financial Liabilities | C57: 398.57 | D57: 428.74 | E57: 544.41 | F57: 335.15 | G57: 348.74
B58: Provisions | C58: 765.81 | D58: 732.94 | E58: 424.58 | F58: 314.99 | G58: 252.25
B59: Deferred Tax Liabilities (Net) | C59: 8443.38 | D59: 8526.67 | E59: 8456.65 | F59: 6997.06 | G59: 8842.78
B60: Other Non-current Liabilities | C60: 16.24 | D60: 76.32 | E60: 132.19 | F60: 127.09 | G60: 87.03
B61: Total Non-current liabilities | C61: 144759.22 | D61: 115335.65 | E61: 112484.81 | F61: =SUM(F54:F60) -> 106802.14 | G61: =SUM(G54:G60) -> 103886.38
B62: Current Liabilities
B63: Financial Liabilities
B64: Borrowings | C64: 34635.46 | D64: 26457.29 | E64: 10037.04 | F64: 11988.13 | G64: 18378.52
B65: Lease Liabilities | C65: 279.91 | D65: 238.16 | E65: 221.13 | F65: 195.7
B66: Supplier's Credit | D66: 183.4
B67: Policyholder's Liabilities | C67: 2077.9 | D67: 3167.74 | E67: 3485.22 | F67: 2348.74 | G67: 2480.54
B68: Trade Payables
B69: - Total Outstanding dues of Micro and Small Enterprises | C69: 351.52 | D69: 244.28 | E69: 150.94 | F69: 83.15 | G69: 36.36
B70: - Total Outstanding dues of creditors other than Micro and Small Enterprises | C70: 13001.75 | D70: 11149.16 | E70: 7971.62 | F70: 6605.44 | G70: 6047.34
B71: Other Financial Liabilities | C71: 9859.01 | D71: 8166.09 | E71: 21647.19 | F71: 17920.54 | G71: 14419.25
B72: Other Current Liabilities | C72: 6438.15 | D72: 6445.02 | E72: 5587.44 | F72: 4561.06 | G72: 4779.31
B73: Provisions | C73: 722.47 | D73: 815.74 | E73: 1080.15 | F73: 1311.82 | G73: 1230.93
B74: Current Tax Liabilities (Net) | C74: 2166.82 | D74: 1017.59 | E74: 1243.21 | F74: 1122.33 | G74: 904.2
B75: Total Current liabilities | C75: 69532.99 | D75: 57884.47 | E75: 51423.94 | F75: =SUM(F64:F74) -> 46136.91 | G75: =SUM(G64:G74) -> 48276.45
B76: Liabilities directly associated with Non-Current Assets Held for Sale | E76: 585.96 | F76: 489 | G76: 489
B77: Total Liabilities | C77: =C61+C75 -> 214292.21 | D77: =D61+D75 -> 173220.12 | E77: =E61+E75 -> 163908.75 | F77: =F61+F75 -> 152939.05 | G77: =G61+G75 -> 152162.83
B78: Total Equity and Liabilities | C78: 337205.03 | D78: 289394.83 | E78: 267056.31 | F78: 244415.8 | G78: 241173.93
B83: No. of Equity Shares (in Crores) | C83: 65.84 | D83: 65.84 | E83: 65.84 | F83: 65.84 | G83: 65.84
B84: MPS (INR) | C84: 1632.7 | D84: 1664 | E84: 1450.55 | F84: 476.1 | G84: 830.15
B85: Value per Share (Book Value) | C85: =C50/C83 -> 1866.8411 | D85: =D50/D83 -> 1764.5005 | E85: =E50/E83 -> 1557.74 | F85: =F50/F83 -> 1381.9525 | G85: =G50/G83 -> 1344.5033
B86: Price to Book Value (P/BV) Ratio | H86: current MPS/P/BV Ratio | J86: Book Value = Total Equity/ No. of equity shares
B89: Table 2.1: Statement of Profit and Loss of Grasim Industries Ltd. (India) | I89: Average Total Assets | J89: =(C43+D43)/2 -> 313299.93 | K89: =(D43+E43)/2 -> 278225.57 | L89: =(E43+F43)/2 -> 255736.05 | M89: =(F43+G43)/2 -> 242794.86 | N89: =(G43+H43)/2 -> 120586.96
B90: for the year ended (₹ in Crores) | I90: Average Networth (Equity) | J90: =(C50+D50)/2 -> 119543.77 | K90: =(D50+E50)/2 -> 109368.15 | L90: =(E50+F50)/2 -> 96774.675 | M90: =(F50+G50)/2 -> 89754.925 | N90: =(G50+H50)/2 -> 44261.05
B91: Particulars | C91: March 31, 2023 | D91: March 31, 2022 | E91: March 31, 2021 | F91: March 31, 2020 | G91: March 31, 2019 | I91: EBIT (Operating Profit) | J91: =C92-C108+(C104+C105) -> 17037.46 | K91: =D92-D108+(D104+D105) -> 16270.3 | L91: =E92-E108+(E104+E105) -> 14595.46 | M91: =F92-F108+(F104+F105) -> 13426.42 | N91: =G92-G108+(G104+G105) -> 13055.14
B92: Revenue from operations | C92: 117627.08 | D92: 95701.13 | E92: 76397.81 | F92: 77625.1 | G92: 77200.25 | I92: EBIT (PAT - Other Income + Finance Cost + Tax -/+ Exceptional Items) or (Revenue from Operations - Total Exp. + Finance Cost)
B93: Other Income | C93: 3612.05 | D93: 821.34 | E93: 1051.96 | F93: 966.61 | G93: 827.69 | I93: EBITDA (EBIT + D&A) | J93: =J91+C106 -> 21589.05 | K93: =K91+D106 -> 20431.37 | L93: =L91+E106 -> 18628.86 | M93: =M91+F106 -> 17467.24 | N93: =N91+G106 -> 16626.52
B94: Total Income (I) | C94: 121239.13 | D94: 96522.47 | E94: 77449.77 | F94: 78591.71 | G94: 78027.94 | I94: Capital Employed (CE) = (TA-CL) | J94: =C43-C75 -> 267672.04 | K94: =D43-D75 -> 231510.36 | L94: =E43-E75 -> 215632.37 | M94: =F43-F75 -> 198278.89 | N94: =G43-G75 -> 192897.48
B95: Expenses | I95: Average Capital Employed | J95: =(J94+K94)/2 -> 249591.2 | K95: =(K94+L94)/2 -> 223571.36 | L95: =(L94+M94)/2 -> 206955.63 | M95: =(M94+N94)/2 -> 195588.18 | N95: =(N94+O94)/2 -> 96448.74
B96: Cost of materials consumed | C96: 21622.26 | D96: 16889.6 | E96: 11006.75 | F96: 14618.05 | G96: 15261.12 | I96: Average Non-current Assets | J96: =(C26+D26)/2 -> 251154.9 | K96: =(D26+E26)/2 -> 219953.05 | L96: =(E26+F26)/2 -> 199674.71 | M96: =(F26+G26)/2 -> 191681.91 | N96: =(G26+H26)/2 -> 95646.68
B97: Purchases of stock-in-trade | C97: 1824.35 | D97: 1404.56 | E97: 898.44 | F97: 1469.86 | G97: 1507.01 | I97: Average Current Assets | J97: =(C41+D41)/2 -> 62131.25 | K97: =(D41+E41)/2 -> 57108.355 | L97: =(E41+F41)/2 -> 28729.275 | M97: =(F41+G41)/2 -> 0 | N97: =(G41+H41)/2 -> 0
B98: Changes in inventories of finished goods, work-in-progress and stock-in-trade | C98: 834.66 | D98: 921.74 | E98: 724.03 | F98: 525.9 | G98: 79.89 | I98: Average Inventory | J98: =(C28+D28)/2 -> 10347.785 | K98: =(D28+E28)/2 -> 7866.69 | L98: =(E28+F28)/2 -> 6501.265 | M98: =(F28+G28)/2 -> 6932.35 | N98: =(G28+H28)/2 -> 3529.565
B99: Employee benefits expense | C99: 7193.86 | D99: 6327.71 | E99: 5534.74 | F99: 5864.53 | G99: 5428.21 | I99: Average Trade Receivables
B100: Power and Fuel | C100: 23168.73 | D100: 15520.7 | E100: 10363.78 | F100: 11436.68 | G100: 12423.45 | I100: Average Trade Payables | J100: =(C69+C70)+(D69+D70)/2 -> 19049.99 | K100: =(D69+D70)+(E69+E70)/2 -> 15454.72 | L100: =(E69+E70)+(F69+F70)/2 -> 11466.855 | M100: =(F69+F70)+(G69+G70)/2 -> 9730.44 | N100: =(G69+G70)+(H69+H70)/2 -> 6083.7
B101: Freight and Handling Expenses | C101: 15024.93 | D101: 12584.1 | E101: 10381.83 | F101: 10058.06 | G101: 10619.15 | I101: Cost of Inventory
B102: Change in Valuation of Liability in respect of Insurance Policies | C102: 7451.57 | D102: 4240.83 | E102: 4374.84 | F102: 1032.26 | G102: 1408.88 | I102: Accounts Payables (A/P) Efficiency Ratio
B103: Benefits Paid - Insurance Business | C103: 5467.75 | D103: 6702.55 | E103: 4445.05 | F103: 5177.01 | G103: 4553.57 | I103: Payables Payment Days (365/APTR)
B104: Finance Cost relating to NBFC/HFC's Business | C104: 4723.46 | D104: 3480.3 | E104: 3914.6 | F104: 4587.82 | G104: 4050.18
B105: Other Finance Costs | C105: 1320.27 | D105: 1295.7 | E105: 1808.88 | F105: 2338.5 | G105: 2009.85 | I105: No. of Equity Shares (in Lakhs) | J105: 65.84 | K105: 65.84 | L105: 65.84 | M105: 65.84 | N105: 65.84
B106: Depreciation and Amortisation expense | C106: 4551.59 | D106: 4161.07 | E106: 4033.4 | F106: 4040.82 | G106: 3571.38 | I106: MPS (INR)
B107: Other Expenses | C107: 15119.24 | D107: 12521.45 | E107: 10069.97 | F107: 11047.77 | G107: 9482.99 | I107: DPS
...
